Workbook

Sheet Instructions, Assumptions
D11: COST BOM sheet
P14: <--Use Option Description under each column to descibe the particular option you are proposing; e.g. Starllink 5Tb solution
R18: RENTAL
P19: <--Use ITEM cell to describe the specific equipment you are proposing; e.g., Starllink Flat High Performance (FHP)
P20: <--Use CATEGORY drop down menu to select the category for the equipment; e.g., LEO VSAT equipment
P21: <--Use UNIT COST to enter the cost for ONE of the equipment items you are proposing
P22: <--Use QUANTITY (QTY) to enter the number of ITEMS you are adding to the assembly; e.g., enter 2 for a dual Starlink antenna maritime solution
P23: <--Use Notes/Comments/Assumptions to describe any non-standard ITEM assumptions e.g., this is a placeholder number until firm pricing is received from vendor
P59: <--Use PURCHASE MARKUP to enter your % markup to calculate sale price for an item, e.g., 40 for a 40% markup on your item; single unit pricing will show in the UNIT SALE PRICE cell
A80: PRICING sheet
M87: <--Use TERM (MONTHS) cell to enter the number of contracted months you are proposing to the customer; e.g. 36 for a 3 year contract
M88: <--Use NUMBER OF SITES cell to enter the number of customer sites with the exact configuration in the corresponding column from the COST BOM
M89: <--Use MONTHLY rate cell to enter the MONTHLY USD rate you are proposing to the customer
M90: <--Use INSTALL & DOWN PAYMENT cell to enter any upront down payment or estimated or fixed charged install

Sheet Rental (BOM)
A1: =Pricing!B1
A3: Customer -> | B3: ='Exec Summary'!C5 | D3: Column 1 | F3: Column 2 | H3: Column 3 | J3: Column 4 | L3: Column 5
C4: Option Description->
A6: Rental Items
D7: Column 1 | F7: Column 2 | H7: Column 3 | J7: Column 4 | L7: Column 5
A8: Item | B8: Category | C8: Unit Cost | D8: Qty | E8: Total Cost | F8: Qty | G8: Total Cost | H8: Qty | I8: Total Cost | J8: Qty | K8: Total Cost | L8: Qty | M8: Total Cost
A9: ASSEMBLY | P9: Notes / Comments / Assumptions
B10: - | C10: 0 | D10: 0 | E10: =SUM(C10*D10) | F10: 0 | G10: =F10*C10 | H10: 0 | I10: =SUM(H10*C10) | J10: 0 | K10: =SUM(J10*C10) | L10: 0 | M10: =SUM(L10*C10)
B11: - | C11: 0 | D11: 0 | E11: =SUM(C11*D11) | F11: 0 | G11: =F11*C11 | H11: 0 | I11: =SUM(H11*C11) | J11: 0 | K11: =SUM(J11*C11) | L11: 0 | M11: =SUM(L11*C11)
B12: - | C12: 0 | D12: 0 | E12: =SUM(C12*D12) | F12: 0 | G12: =F12*C12 | H12: 0 | I12: =SUM(H12*C12) | J12: 0 | K12: =SUM(J12*C12) | L12: 0 | M12: =SUM(L12*C12)
B13: - | C13: 0 | D13: 0 | E13: =SUM(C13*D13) | F13: 0 | G13: =F13*C13 | H13: 0 | I13: =SUM(H13*C13) | J13: 0 | K13: =SUM(J13*C13) | L13: 0 | M13: =SUM(L13*C13)
B14: - | C14: 0 | D14: 0 | E14: =SUM(C14*D14) | F14: 0 | G14: =F14*C14 | H14: 0 | I14: =SUM(H14*C14) | J14: 0 | K14: =SUM(J14*C14) | L14: 0 | M14: =SUM(L14*C14)
B15: - | C15: 0 | D15: 0 | E15: =SUM(C15*D15) | F15: 0 | G15: =F15*C15 | H15: 0 | I15: =SUM(H15*C15) | J15: 0 | K15: =SUM(J15*C15) | L15: 0 | M15: =SUM(L15*C15)
B16: - | C16: 0 | D16: 0 | E16: =SUM(C16*D16) | F16: 0 | G16: =F16*C16 | H16: 0 | I16: =SUM(H16*C16) | J16: 0 | K16: =SUM(J16*C16) | L16: 0 | M16: =SUM(L16*C16)
B17: - | C17: 0 | D17: 0 | E17: =SUM(C17*D17) | F17: 0 | G17: =F17*C17 | H17: 0 | I17: =SUM(H17*C17) | J17: 0 | K17: =SUM(J17*C17) | L17: 0 | M17: =SUM(L17*C17)
B18: - | C18: 0 | D18: 0 | E18: =SUM(C18*D18) | F18: 0 | G18: =F18*C18 | H18: 0 | I18: =SUM(H18*C18) | J18: 0 | K18: =SUM(J18*C18) | L18: 0 | M18: =SUM(L18*C18)
B19: - | C19: 0 | D19: 0 | E19: =SUM(C19*D19) | F19: 0 | G19: =F19*C19 | H19: 0 | I19: =SUM(H19*C19) | J19: 0 | K19: =SUM(J19*C19) | L19: 0 | M19: =SUM(L19*C19)
B20: - | C20: 0 | D20: 0 | E20: =SUM(C20*D20) | F20: 0 | G20: =F20*C20 | H20: 0 | I20: =SUM(H20*C20) | J20: 0 | K20: =SUM(J20*C20) | L20: 0 | M20: =SUM(L20*C20)
B21: - | C21: 0 | D21: 0 | E21: =SUM(C21*D21) | F21: 0 | G21: =F21*C21 | H21: 0 | I21: =SUM(H21*C21) | J21: 0 | K21: =SUM(J21*C21) | L21: 0 | M21: =SUM(L21*C21)
... B64: - | C64: 0 | D64: 0 | E64: =SUM(C64*D64) | F64: 0 | G64: =F64*C64 | H64: 0 | I64: =SUM(H64*C64) | J64: 0 | K64: =SUM(J64*C64) | L64: 0 | M64: =SUM(L64*C64)
A65: ANCILLARY ITEMS
B66: - | C66: 0 | D66: 0 | E66: =SUM(C66*D66) | F66: 0 | G66: =SUM(F66*C66) | H66: 0 | I66: =SUM(H66*C66) | J66: 0 | K66: =SUM(J66*C66) | L66: 0 | M66: =SUM(L66*C66)
B67: - | C67: 0 | D67: 0 | E67: =SUM(C67*D67) | F67: 0 | G67: =F67*C67 | H67: 0 | I67: =SUM(H67*C67) | J67: 0 | K67: =SUM(J67*C67) | L67: 0 | M67: =SUM(L67*C67)
B68: - | C68: 0 | D68: 0 | E68: =SUM(C68*D68) | F68: 0 | G68: =F68*C68 | H68: 0 | I68: =SUM(H68*C68) | J68: 0 | K68: =SUM(J68*C68) | L68: 0 | M68: =SUM(L68*C68)
B69: - | C69: 0 | D69: 0 | E69: =SUM(C69*D69) | F69: 0 | G69: =F69*C69 | H69: 0 | I69: =SUM(H69*C69) | J69: 0 | K69: =SUM(J69*C69) | L69: 0 | M69: =SUM(L69*C69)
B70: - | C70: 0 | D70: 0 | E70: =SUM(C70*D70) | F70: 0 | G70: =F70*C70 | H70: 0 | I70: =SUM(H70*C70) | J70: 0 | K70: =SUM(J70*C70) | L70: 0 | M70: =SUM(L70*C70)
B71: - | C71: 0 | D71: 0 | E71: =SUM(C71*D71) | F71: 0 | G71: =F71*C71 | H71: 0 | I71: =SUM(H71*C71) | J71: 0 | K71: =SUM(J71*C71) | L71: 0 | M71: =SUM(L71*C71)
B72: - | C72: 0 | D72: 0 | E72: =SUM(C72*D72) | F72: 0 | G72: =F72*C72 | H72: 0 | I72: =SUM(H72*C72) | J72: 0 | K72: =SUM(J72*C72) | L72: 0 | M72: =SUM(L72*C72)
B73: - | C73: 0 | D73: 0 | E73: =SUM(C73*D73) | F73: 0 | G73: =F73*C73 | H73: 0 | I73: =SUM(H73*C73) | J73: 0 | K73: =SUM(J73*C73) | L73: 0 | M73: =SUM(L73*C73)
B74: - | C74: 0 | D74: 0 | E74: =SUM(C74*D74) | F74: 0 | G74: =F74*C74 | H74: 0 | I74: =SUM(H74*C74) | J74: 0 | K74: =SUM(J74*C74) | L74: 0 | M74: =SUM(L74*C74)
B75: - | C75: 0 | D75: 0 | E75: =SUM(C75*D75) | F75: 0 | G75: =F75*C75 | H75: 0 | I75: =SUM(H75*C75) | J75: 0 | K75: =SUM(J75*C75) | L75: 0 | M75: =SUM(L75*C75)
B76: - | C76: 0 | D76: 0 | E76: =SUM(C76*D76) | F76: 0 | G76: =F76*C76 | H76: 0 | I76: =SUM(H76*C76) | J76: 0 | K76: =SUM(J76*C76) | L76: 0 | M76: =SUM(L76*C76)
B77: - | C77: 0 | D77: 0 | E77: =SUM(C77*D77) | F77: 0 | G77: =F77*C77 | H77: 0 | I77: =SUM(H77*C77) | J77: 0 | K77: =SUM(J77*C77) | L77: 0 | M77: =SUM(L77*C77)
B78: - | C78: 0 | D78: 0 | E78: =SUM(C78*D78) | F78: 0 | G78: =F78*C78 | H78: 0 | I78: =SUM(H78*C78) | J78: 0 | K78: =SUM(J78*C78) | L78: 0 | M78: =SUM(L78*C78)
... B103: - | C103: 0 | D103: 0 | E103: =SUM(C103*D103) | F103: 0 | G103: =F103*C103 | H103: 0 | I103: =SUM(H103*C103) | J103: 0 | K103: =SUM(J103*C103) | L103: 0 | M103: =SUM(L103*C103)
B104: - | C104: 0 | D104: 0 | E104: =SUM(C104*D104) | F104: 0 | G104: =SUM(F104*C104) | H104: 0 | I104: =SUM(H104*C104) | J104: 0 | K104: =SUM(J104*C104) | L104: 0 | M104: =SUM(L104*C104)
A105: INSTALLATION
B106: - | C106: 0 | D106: 0 | E106: =SUM(C106*D106) | F106: 0 | G106: =SUM(F106*C106) | H106: 0 | I106: =SUM(H106*C106) | J106: 0 | K106: =SUM(J106*C106) | L106: 0 | M106: =SUM(L106*C106)
B107: - | C107: 0 | D107: 0 | E107: =SUM(C107*D107) | F107: 0 | G107: =F107*C107 | H107: 0 | I107: =SUM(H107*C107) | J107: 0 | K107: =SUM(J107*C107) | L107: 0 | M107: =SUM(L107*C107)
B108: - | C108: 0 | D108: 0 | E108: =SUM(C108*D108) | F108: 0 | G108: =F108*C108 | H108: 0 | I108: =SUM(H108*C108) | J108: 0 | K108: =SUM(J108*C108) | L108: 0 | M108: =SUM(L108*C108)
B109: - | C109: 0 | D109: 0 | E109: =SUM(C109*D109) | F109: 0 | G109: =F109*C109 | H109: 0 | I109: =SUM(H109*C109) | J109: 0 | K109: =SUM(J109*C109) | L109: 0 | M109: =SUM(L109*C109)
B110: - | C110: 0 | D110: 0 | E110: =SUM(C110*D110) | F110: 0 | G110: =F110*C110 | H110: 0 | I110: =SUM(H110*C110) | J110: 0 | K110: =SUM(J110*C110) | L110: 0 | M110: =SUM(L110*C110)
B111: - | C111: 0 | D111: 0 | E111: =SUM(C111*D111) | F111: 0 | G111: =F111*C111 | H111: 0 | I111: =SUM(H111*C111) | J111: 0 | K111: =SUM(J111*C111) | L111: 0 | M111: =SUM(L111*C111)
B112: - | C112: 0 | D112: 0 | E112: =SUM(C112*D112) | F112: 0 | G112: =F112*C112 | H112: 0 | I112: =SUM(H112*C112) | J112: 0 | K112: =SUM(J112*C112) | L112: 0 | M112: =SUM(L112*C112)
B113: - | C113: 0 | D113: 0 | E113: =SUM(C113*D113) | F113: 0 | G113: =F113*C113 | H113: 0 | I113: =SUM(H113*C113) | J113: 0 | K113: =SUM(J113*C113) | L113: 0 | M113: =SUM(L113*C113)
B114: - | C114: 0 | D114: 0 | E114: =SUM(C114*D114) | F114: 0 | G114: =F114*C114 | H114: 0 | I114: =SUM(H114*C114) | J114: 0 | K114: =SUM(J114*C114) | L114: 0 | M114: =SUM(L114*C114)
B115: - | C115: 0 | D115: 0 | E115: =SUM(C115*D115) | F115: 0 | G115: =F115*C115 | H115: 0 | I115: =SUM(H115*C115) | J115: 0 | K115: =SUM(J115*C115) | L115: 0 | M115: =SUM(L115*C115)
B116: - | C116: 0 | D116: 0 | E116: =SUM(C116*D116) | F116: 0 | G116: =F116*C116 | H116: 0 | I116: =SUM(H116*C116) | J116: 0 | K116: =SUM(J116*C116) | L116: 0 | M116: =SUM(L116*C116)
B117: - | C117: 0 | D117: 0 | E117: =SUM(C117*D117) | F117: 0 | G117: =F117*C117 | H117: 0 | I117: =SUM(H117*C117) | J117: 0 | K117: =SUM(J117*C117) | L117: 0 | M117: =SUM(L117*C117)
B118: - | C118: 0 | D118: 0 | E118: =SUM(C118*D118) | F118: 0 | G118: =F118*C118 | H118: 0 | I118: =SUM(H118*C118) | J118: 0 | K118: =SUM(J118*C118) | L118: 0 | M118: =SUM(L118*C118)
... B125: - | C125: 0 | D125: 0 | E125: =SUM(C125*D125) | F125: 0 | G125: =F125*C125 | H125: 0 | I125: =SUM(H125*C125) | J125: 0 | K125: =SUM(J125*C125) | L125: 0 | M125: =SUM(L125*C125)
B126: - | C126: 0 | D126: 0 | E126: =SUM(C126*D126) | F126: 0 | G126: =SUM(F126*C126) | H126: 0 | I126: =SUM(H126*C126) | J126: 0 | K126: =SUM(J126*C126) | L126: 0 | M126: =SUM(L126*C126)
A127: RECURRING
B128: - | C128: 0 | D128: 0 | E128: =SUM(C128*D128) | F128: 0 | G128: =F128*C128 | H128: 0 | I128: =SUM(H128*C128) | J128: 0 | K128: =SUM(J128*C128) | L128: 0 | M128: =SUM(L128*C128)
B129: - | C129: 0 | D129: 0 | E129: =SUM(C129*D129) | F129: 0 | G129: =F129*C129 | H129: 0 | I129: =SUM(H129*C129) | J129: 0 | K129: =SUM(J129*C129) | L129: 0 | M129: =SUM(L129*C129)
B130: - | C130: 0 | D130: 0 | E130: =SUM(C130*D130) | F130: 0 | G130: =F130*C130 | H130: 0 | I130: =SUM(H130*C130) | J130: 0 | K130: =SUM(J130*C130) | L130: 0 | M130: =SUM(L130*C130)
B131: - | C131: 0 | D131: 0 | E131: =SUM(C131*D131) | F131: 0 | G131: =F131*C131 | H131: 0 | I131: =SUM(H131*C131) | J131: 0 | K131: =SUM(J131*C131) | L131: 0 | M131: =SUM(L131*C131)
B132: - | C132: 0 | D132: 0 | E132: =SUM(C132*D132) | F132: 0 | G132: =F132*C132 | H132: 0 | I132: =SUM(H132*C132) | J132: 0 | K132: =SUM(J132*C132) | L132: 0 | M132: =SUM(L132*C132)
B133: - | C133: 0 | D133: 0 | E133: =SUM(C133*D133) | F133: 0 | G133: =F133*C133 | H133: 0 | I133: =SUM(H133*C133) | J133: 0 | K133: =SUM(J133*C133) | L133: 0 | M133: =SUM(L133*C133)
B134: - | C134: 0 | D134: 0 | E134: =SUM(C134*D134) | F134: 0 | G134: =F134*C134 | H134: 0 | I134: =SUM(H134*C134) | J134: 0 | K134: =SUM(J134*C134) | L134: 0 | M134: =SUM(L134*C134)
B135: - | C135: 0 | D135: 0 | E135: =SUM(C135*D135) | F135: 0 | G135: =F135*C135 | H135: 0 | I135: =SUM(H135*C135) | J135: 0 | K135: =SUM(J135*C135) | L135: 0 | M135: =SUM(L135*C135)
B136: - | C136: 0 | D136: 0 | E136: =SUM(C136*D136) | F136: 0 | G136: =F136*C136 | H136: 0 | I136: =SUM(H136*C136) | J136: 0 | K136: =SUM(J136*C136) | L136: 0 | M136: =SUM(L136*C136)
B137: - | C137: 0 | D137: 0 | E137: =SUM(C137*D137) | F137: 0 | G137: =F137*C137 | H137: 0 | I137: =SUM(H137*C137) | J137: 0 | K137: =SUM(J137*C137) | L137: 0 | M137: =SUM(L137*C137)
B138: - | C138: 0 | D138: 0 | E138: =SUM(C138*D138) | F138: 0 | G138: =F138*C138 | H138: 0 | I138: =SUM(H138*C138) | J138: 0 | K138: =SUM(J138*C138) | L138: 0 | M138: =SUM(L138*C138)
B139: - | C139: 0 | D139: 0 | E139: =SUM(C139*D139) | F139: 0 | G139: =F139*C139 | H139: 0 | I139: =SUM(H139*C139) | J139: 0 | K139: =SUM(J139*C139) | L139: 0 | M139: =SUM(L139*C139)
... B150: - | C150: 0 | D150: 0 | E150: =SUM(C150*D150) | F150: 0 | G150: =F150*C150 | H150: 0 | I150: =SUM(H150*C150) | J150: 0 | K150: =SUM(J150*C150) | L150: 0 | M150: =SUM(L150*C150)

Sheet Sale (BOM)
A1: =Pricing!B1
A3: Customer -> | B3: ='Exec Summary'!C5
A5: Sale Items
F6: Column 1 | I6: Column 2 | L6: Column 3 | O6: Column 4 | R6: Column 5
E7: Description-->
A8: Item | B8: Category | C8: Unit Cost | D8: Target Margin | E8: Unit Sales Price | F8: Qty | G8: Total Cost | H8: Total Sale Price | I8: Qty | J8: Total Cost | K8: Total Sale Price | L8: Qty | M8: Total Cost | N8: Total Sale Price | O8: Qty | P8: Total Cost | Q8: Total Sale Price | R8: Qty | S8: Total Cost | T8: Total Sale Price
A9: ASSEMBLY | W9: Notes / Comments / Assumptions
B10: - | C10: 0 | D10: 0 | E10: =IFERROR(C10/(1-D10),0) | F10: 0 | G10: =SUM(C10*F10) | H10: =SUM(E10*F10) | I10: 0 | J10: =SUM(I10*C10) | K10: =SUM(E10*I10) | L10: 0 | M10: =SUM(L10*C10) | N10: =SUM(E10*L10) | O10: 0 | P10: =SUM(O10*C10) | Q10: =SUM(E10*O10) | R10: 0 | S10: =SUM(R10*C10) | T10: =SUM(E10*R10)
B11: - | C11: 0 | D11: 0 | E11: =IFERROR(C11/(1-D11),0) | F11: 0 | G11: =SUM(C11*F11) | H11: =SUM(E11*F11) | I11: 0 | J11: =SUM(I11*C11) | K11: =SUM(E11*I11) | L11: 0 | M11: =SUM(L11*C11) | N11: =SUM(E11*L11) | O11: 0 | P11: =SUM(O11*C11) | Q11: =SUM(E11*O11) | R11: 0 | S11: =SUM(R11*C11) | T11: =SUM(E11*R11)
B12: - | C12: 0 | D12: 0 | E12: =IFERROR(C12/(1-D12),0) | F12: 0 | G12: =SUM(C12*F12) | H12: =SUM(E12*F12) | I12: 0 | J12: =SUM(I12*C12) | K12: =SUM(E12*I12) | L12: 0 | M12: =SUM(L12*C12) | N12: =SUM(E12*L12) | O12: 0 | P12: =SUM(O12*C12) | Q12: =SUM(E12*O12) | R12: 0 | S12: =SUM(R12*C12) | T12: =SUM(E12*R12)
B13: - | C13: 0 | D13: 0 | E13: =IFERROR(C13/(1-D13),0) | F13: 0 | G13: =SUM(C13*F13) | H13: =SUM(E13*F13) | I13: 0 | J13: =SUM(I13*C13) | K13: =SUM(E13*I13) | L13: 0 | M13: =SUM(L13*C13) | N13: =SUM(E13*L13) | O13: 0 | P13: =SUM(O13*C13) | Q13: =SUM(E13*O13) | R13: 0 | S13: =SUM(R13*C13) | T13: =SUM(E13*R13)
B14: - | C14: 0 | D14: 0 | E14: =IFERROR(C14/(1-D14),0) | F14: 0 | G14: =SUM(C14*F14) | H14: =SUM(E14*F14) | I14: 0 | J14: =SUM(I14*C14) | K14: =SUM(E14*I14) | L14: 0 | M14: =SUM(L14*C14) | N14: =SUM(E14*L14) | O14: 0 | P14: =SUM(O14*C14) | Q14: =SUM(E14*O14) | R14: 0 | S14: =SUM(R14*C14) | T14: =SUM(E14*R14)
B15: - | C15: 0 | D15: 0 | E15: =IFERROR(C15/(1-D15),0) | F15: 0 | G15: =SUM(C15*F15) | H15: =SUM(E15*F15) | I15: 0 | J15: =SUM(I15*C15) | K15: =SUM(E15*I15) | L15: 0 | M15: =SUM(L15*C15) | N15: =SUM(E15*L15) | O15: 0 | P15: =SUM(O15*C15) | Q15: =SUM(E15*O15) | R15: 0 | S15: =SUM(R15*C15) | T15: =SUM(E15*R15)
B16: - | C16: 0 | D16: 0 | E16: =IFERROR(C16/(1-D16),0) | F16: 0 | G16: =SUM(C16*F16) | H16: =SUM(E16*F16) | I16: 0 | J16: =SUM(I16*C16) | K16: =SUM(E16*I16) | L16: 0 | M16: =SUM(L16*C16) | N16: =SUM(E16*L16) | O16: 0 | P16: =SUM(O16*C16) | Q16: =SUM(E16*O16) | R16: 0 | S16: =SUM(R16*C16) | T16: =SUM(E16*R16)
B17: - | C17: 0 | D17: 0 | E17: =IFERROR(C17/(1-D17),0) | F17: 0 | G17: =SUM(C17*F17) | H17: =SUM(E17*F17) | I17: 0 | J17: =SUM(I17*C17) | K17: =SUM(E17*I17) | L17: 0 | M17: =SUM(L17*C17) | N17: =SUM(E17*L17) | O17: 0 | P17: =SUM(O17*C17) | Q17: =SUM(E17*O17) | R17: 0 | S17: =SUM(R17*C17) | T17: =SUM(E17*R17)
B18: - | C18: 0 | D18: 0 | E18: =IFERROR(C18/(1-D18),0) | F18: 0 | G18: =SUM(C18*F18) | H18: =SUM(E18*F18) | I18: 0 | J18: =SUM(I18*C18) | K18: =SUM(E18*I18) | L18: 0 | M18: =SUM(L18*C18) | N18: =SUM(E18*L18) | O18: 0 | P18: =SUM(O18*C18) | Q18: =SUM(E18*O18) | R18: 0 | S18: =SUM(R18*C18) | T18: =SUM(E18*R18)
B19: - | C19: 0 | D19: 0 | E19: =IFERROR(C19/(1-D19),0) | F19: 0 | G19: =SUM(C19*F19) | H19: =SUM(E19*F19) | I19: 0 | J19: =SUM(I19*C19) | K19: =SUM(E19*I19) | L19: 0 | M19: =SUM(L19*C19) | N19: =SUM(E19*L19) | O19: 0 | P19: =SUM(O19*C19) | Q19: =SUM(E19*O19) | R19: 0 | S19: =SUM(R19*C19) | T19: =SUM(E19*R19)
B20: - | C20: 0 | D20: 0 | E20: =IFERROR(C20/(1-D20),0) | F20: 0 | G20: =SUM(C20*F20) | H20: =SUM(E20*F20) | I20: 0 | J20: =SUM(I20*C20) | K20: =SUM(E20*I20) | L20: 0 | M20: =SUM(L20*C20) | N20: =SUM(E20*L20) | O20: 0 | P20: =SUM(O20*C20) | Q20: =SUM(E20*O20) | R20: 0 | S20: =SUM(R20*C20) | T20: =SUM(E20*R20)
B21: - | C21: 0 | D21: 0 | E21: =IFERROR(C21/(1-D21),0) | F21: 0 | G21: =SUM(C21*F21) | H21: =SUM(E21*F21) | I21: 0 | J21: =SUM(I21*C21) | K21: =SUM(E21*I21) | L21: 0 | M21: =SUM(L21*C21) | N21: =SUM(E21*L21) | O21: 0 | P21: =SUM(O21*C21) | Q21: =SUM(E21*O21) | R21: 0 | S21: =SUM(R21*C21) | T21: =SUM(E21*R21)
... B28: - | C28: 0 | D28: 0 | E28: =IFERROR(C28/(1-D28),0) | F28: 0 | G28: =SUM(C28*F28) | H28: =SUM(E28*F28) | I28: 0 | J28: =SUM(I28*C28) | K28: =SUM(E28*I28) | L28: 0 | M28: =SUM(L28*C28) | N28: =SUM(E28*L28) | O28: 0 | P28: =SUM(O28*C28) | Q28: =SUM(E28*O28) | R28: 0 | S28: =SUM(R28*C28) | T28: =SUM(E28*R28)
A29: ANCILLARY ITEMS
B30: - | C30: 0 | D30: 0 | E30: =IFERROR(C30/(1-D30),0) | F30: 0 | G30: =SUM(C30*F30) | H30: =SUM(E30*F30) | I30: 0 | J30: =SUM(I30*C30) | K30: =SUM(E30*I30) | L30: 0 | M30: =SUM(L30*C30) | N30: =SUM(E30*L30) | O30: 0 | P30: =SUM(O30*C30) | Q30: =SUM(E30*O30) | R30: 0 | S30: =SUM(R30*C30) | T30: =SUM(E30*R30)
B31: - | C31: 0 | D31: 0 | E31: =IFERROR(C31/(1-D31),0) | F31: 0 | G31: =SUM(C31*F31) | H31: =SUM(E31*F31) | I31: 0 | J31: =SUM(I31*C31) | K31: =SUM(E31*I31) | L31: 0 | M31: =SUM(L31*C31) | N31: =SUM(E31*L31) | O31: 0 | P31: =SUM(O31*C31) | Q31: =SUM(E31*O31) | R31: 0 | S31: =SUM(R31*C31) | T31: =SUM(E31*R31)
B32: - | C32: 0 | D32: 0 | E32: =IFERROR(C32/(1-D32),0) | F32: 0 | G32: =SUM(C32*F32) | H32: =SUM(E32*F32) | I32: 0 | J32: =SUM(I32*C32) | K32: =SUM(E32*I32) | L32: 0 | M32: =SUM(L32*C32) | N32: =SUM(E32*L32) | O32: 0 | P32: =SUM(O32*C32) | Q32: =SUM(E32*O32) | R32: 0 | S32: =SUM(R32*C32) | T32: =SUM(E32*R32)
B33: - | C33: 0 | D33: 0 | E33: =IFERROR(C33/(1-D33),0) | F33: 0 | G33: =SUM(C33*F33) | H33: =SUM(E33*F33) | I33: 0 | J33: =SUM(I33*C33) | K33: =SUM(E33*I33) | L33: 0 | M33: =SUM(L33*C33) | N33: =SUM(E33*L33) | O33: 0 | P33: =SUM(O33*C33) | Q33: =SUM(E33*O33) | R33: 0 | S33: =SUM(R33*C33) | T33: =SUM(E33*R33)
B34: - | C34: 0 | D34: 0 | E34: =IFERROR(C34/(1-D34),0) | F34: 0 | G34: =SUM(C34*F34) | H34: =SUM(E34*F34) | I34: 0 | J34: =SUM(I34*C34) | K34: =SUM(E34*I34) | L34: 0 | M34: =SUM(L34*C34) | N34: =SUM(E34*L34) | O34: 0 | P34: =SUM(O34*C34) | Q34: =SUM(E34*O34) | R34: 0 | S34: =SUM(R34*C34) | T34: =SUM(E34*R34)
B35: - | C35: 0 | D35: 0 | E35: =IFERROR(C35/(1-D35),0) | F35: 0 | G35: =SUM(C35*F35) | H35: =SUM(E35*F35) | I35: 0 | J35: =SUM(I35*C35) | K35: =SUM(E35*I35) | L35: 0 | M35: =SUM(L35*C35) | N35: =SUM(E35*L35) | O35: 0 | P35: =SUM(O35*C35) | Q35: =SUM(E35*O35) | R35: 0 | S35: =SUM(R35*C35) | T35: =SUM(E35*R35)
B36: - | C36: 0 | D36: 0 | E36: =IFERROR(C36/(1-D36),0) | F36: 0 | G36: =SUM(C36*F36) | H36: =SUM(E36*F36) | I36: 0 | J36: =SUM(I36*C36) | K36: =SUM(E36*I36) | L36: 0 | M36: =SUM(L36*C36) | N36: =SUM(E36*L36) | O36: 0 | P36: =SUM(O36*C36) | Q36: =SUM(E36*O36) | R36: 0 | S36: =SUM(R36*C36) | T36: =SUM(E36*R36)
B37: - | C37: 0 | D37: 0 | E37: =IFERROR(C37/(1-D37),0) | F37: 0 | G37: =SUM(C37*F37) | H37: =SUM(E37*F37) | I37: 0 | J37: =SUM(I37*C37) | K37: =SUM(E37*I37) | L37: 0 | M37: =SUM(L37*C37) | N37: =SUM(E37*L37) | O37: 0 | P37: =SUM(O37*C37) | Q37: =SUM(E37*O37) | R37: 0 | S37: =SUM(R37*C37) | T37: =SUM(E37*R37)
B38: - | C38: 0 | D38: 0 | E38: =IFERROR(C38/(1-D38),0) | F38: 0 | G38: =SUM(C38*F38) | H38: =SUM(E38*F38) | I38: 0 | J38: =SUM(I38*C38) | K38: =SUM(E38*I38) | L38: 0 | M38: =SUM(L38*C38) | N38: =SUM(E38*L38) | O38: 0 | P38: =SUM(O38*C38) | Q38: =SUM(E38*O38) | R38: 0 | S38: =SUM(R38*C38) | T38: =SUM(E38*R38)
B39: - | C39: 0 | D39: 0 | E39: =IFERROR(C39/(1-D39),0) | F39: 0 | G39: =SUM(C39*F39) | H39: =SUM(E39*F39) | I39: 0 | J39: =SUM(I39*C39) | K39: =SUM(E39*I39) | L39: 0 | M39: =SUM(L39*C39) | N39: =SUM(E39*L39) | O39: 0 | P39: =SUM(O39*C39) | Q39: =SUM(E39*O39) | R39: 0 | S39: =SUM(R39*C39) | T39: =SUM(E39*R39)
B40: - | C40: 0 | D40: 0 | E40: =IFERROR(C40/(1-D40),0) | F40: 0 | G40: =SUM(C40*F40) | H40: =SUM(E40*F40) | I40: 0 | J40: =SUM(I40*C40) | K40: =SUM(E40*I40) | L40: 0 | M40: =SUM(L40*C40) | N40: =SUM(E40*L40) | O40: 0 | P40: =SUM(O40*C40) | Q40: =SUM(E40*O40) | R40: 0 | S40: =SUM(R40*C40) | T40: =SUM(E40*R40)
B41: - | C41: 0 | D41: 0 | E41: =IFERROR(C41/(1-D41),0) | F41: 0 | G41: =SUM(C41*F41) | H41: =SUM(E41*F41) | I41: 0 | J41: =SUM(I41*C41) | K41: =SUM(E41*I41) | L41: 0 | M41: =SUM(L41*C41) | N41: =SUM(E41*L41) | O41: 0 | P41: =SUM(O41*C41) | Q41: =SUM(E41*O41) | R41: 0 | S41: =SUM(R41*C41) | T41: =SUM(E41*R41)
A42: INSTALLATION
B43: - | C43: 0 | D43: 0 | E43: =IFERROR(C43/(1-D43),0) | F43: 0 | G43: =SUM(C43*F43) | H43: =SUM(E43*F43) | I43: 0 | J43: =SUM(I43*C43) | K43: =SUM(E43*I43) | L43: 0 | M43: =SUM(L43*C43) | N43: =SUM(E43*L43) | O43: 0 | P43: =SUM(O43*C43) | Q43: =SUM(E43*O43) | R43: 0 | S43: =SUM(R43*C43) | T43: =SUM(E43*R43)
B44: - | C44: 0 | D44: 0 | E44: =IFERROR(C44/(1-D44),0) | F44: 0 | G44: =SUM(C44*F44) | H44: =SUM(E44*F44) | I44: 0 | J44: =SUM(I44*C44) | K44: =SUM(E44*I44) | L44: 0 | M44: =SUM(L44*C44) | N44: =SUM(E44*L44) | O44: 0 | P44: =SUM(O44*C44) | Q44: =SUM(E44*O44) | R44: 0 | S44: =SUM(R44*C44) | T44: =SUM(E44*R44)
B45: - | C45: 0 | D45: 0 | E45: =IFERROR(C45/(1-D45),0) | F45: 0 | G45: =SUM(C45*F45) | H45: =SUM(E45*F45) | I45: 0 | J45: =SUM(I45*C45) | K45: =SUM(E45*I45) | L45: 0 | M45: =SUM(L45*C45) | N45: =SUM(E45*L45) | O45: 0 | P45: =SUM(O45*C45) | Q45: =SUM(E45*O45) | R45: 0 | S45: =SUM(R45*C45) | T45: =SUM(E45*R45)
B46: - | C46: 0 | D46: 0 | E46: =IFERROR(C46/(1-D46),0) | F46: 0 | G46: =SUM(C46*F46) | H46: =SUM(E46*F46) | I46: 0 | J46: =SUM(I46*C46) | K46: =SUM(E46*I46) | L46: 0 | M46: =SUM(L46*C46) | N46: =SUM(E46*L46) | O46: 0 | P46: =SUM(O46*C46) | Q46: =SUM(E46*O46) | R46: 0 | S46: =SUM(R46*C46) | T46: =SUM(E46*R46)
B47: - | C47: 0 | D47: 0 | E47: =IFERROR(C47/(1-D47),0) | F47: 0 | G47: =SUM(C47*F47) | H47: =SUM(E47*F47) | I47: 0 | J47: =SUM(I47*C47) | K47: =SUM(E47*I47) | L47: 0 | M47: =SUM(L47*C47) | N47: =SUM(E47*L47) | O47: 0 | P47: =SUM(O47*C47) | Q47: =SUM(E47*O47) | R47: 0 | S47: =SUM(R47*C47) | T47: =SUM(E47*R47)
B48: - | C48: 0 | D48: 0 | E48: =IFERROR(C48/(1-D48),0) | F48: 0 | G48: =SUM(C48*F48) | H48: =SUM(E48*F48) | I48: 0 | J48: =SUM(I48*C48) | K48: =SUM(E48*I48) | L48: 0 | M48: =SUM(L48*C48) | N48: =SUM(E48*L48) | O48: 0 | P48: =SUM(O48*C48) | Q48: =SUM(E48*O48) | R48: 0 | S48: =SUM(R48*C48) | T48: =SUM(E48*R48)
B49: - | C49: 0 | D49: 0 | E49: =IFERROR(C49/(1-D49),0) | F49: 0 | G49: =SUM(C49*F49) | H49: =SUM(E49*F49) | I49: 0 | J49: =SUM(I49*C49) | K49: =SUM(E49*I49) | L49: 0 | M49: =SUM(L49*C49) | N49: =SUM(E49*L49) | O49: 0 | P49: =SUM(O49*C49) | Q49: =SUM(E49*O49) | R49: 0 | S49: =SUM(R49*C49) | T49: =SUM(E49*R49)
B50: - | C50: 0 | D50: 0 | E50: =IFERROR(C50/(1-D50),0) | F50: 0 | G50: =SUM(C50*F50) | H50: =SUM(E50*F50) | I50: 0 | J50: =SUM(I50*C50) | K50: =SUM(E50*I50) | L50: 0 | M50: =SUM(L50*C50) | N50: =SUM(E50*L50) | O50: 0 | P50: =SUM(O50*C50) | Q50: =SUM(E50*O50) | R50: 0 | S50: =SUM(R50*C50) | T50: =SUM(E50*R50)
B51: - | C51: 0 | D51: 0 | E51: =IFERROR(C51/(1-D51),0) | F51: 0 | G51: =SUM(C51*F51) | H51: =SUM(E51*F51) | I51: 0 | J51: =SUM(I51*C51) | K51: =SUM(E51*I51) | L51: 0 | M51: =SUM(L51*C51) | N51: =SUM(E51*L51) | O51: 0 | P51: =SUM(O51*C51) | Q51: =SUM(E51*O51) | R51: 0 | S51: =SUM(R51*C51) | T51: =SUM(E51*R51)
B52: - | C52: 0 | D52: 0 | E52: =IFERROR(C52/(1-D52),0) | F52: 0 | G52: =SUM(C52*F52) | H52: =SUM(E52*F52) | I52: 0 | J52: =SUM(I52*C52) | K52: =SUM(E52*I52) | L52: 0 | M52: =SUM(L52*C52) | N52: =SUM(E52*L52) | O52: 0 | P52: =SUM(O52*C52) | Q52: =SUM(E52*O52) | R52: 0 | S52: =SUM(R52*C52) | T52: =SUM(E52*R52)

Sheet Pricing
B1: Satellite: P = Version 2026-08-28
B2: Rental/Lease Site(s) Options | E2: 1 | F2: 2 | G2: 3 | H2: 4 | I2: 5 | L2: Notes / Comments / Assumptions
B3: Option Description | D3: → | E3: ='Rental (BOM)'!D4 | F3: ='Rental (BOM)'!F4 | G3: ='Rental (BOM)'!H4 | H3: ='Rental (BOM)'!J4 | I3: ='Rental (BOM)'!L4
B4: Term (Months) | D4: → | E4: 0 | F4: 0 | G4: 0 | H4: 0 | I4: 0
B5: Number of Sites (Same Configuration) | D5: → | E5: 0 | F5: 0 | G5: 0 | H5: 0 | I5: 0
B6: Monthly Rate per site | D6: → | E6: 0 | F6: 0 | G6: 0 | H6: 0 | I6: 0
B7: Flat Rate Installation or Down Payment | D7: → | E7: 0 | F7: 0 | G7: 0 | H7: 0 | I7: 0
B10: Rental/Lease Items | D10: Summary | E10: 1 | F10: 2 | G10: 3 | H10: 4 | I10: 5
B11: Materials Cost | D11: =SUM(D12:D22) | E11: =SUM(E12:E22) | F11: =SUM(F12:F22) | G11: =SUM(G12:G22) | H11: =SUM(H12:H22) | I11: =SUM(I12:I22)
B12: Install Equipment | D12: =SUM(E12,F12,G12,H12,I12) | E12: =SUMIF('Rental (BOM)'!$B$10:$B$104,Pricing!B12,'Rental (BOM)'!$E$10:$E$104)*$E$5 | F12: =SUMIF('Rental (BOM)'!$B$10:$B$104,Pricing!B12,'Rental (BOM)'!$G$10:$G$104)*$F$5 | G12: =SUMIF('Rental (BOM)'!$B$10:$B$104,Pricing!B12,'Rental (BOM)'!$I$10:$I$104)*$G$5 | H12: =SUMIF('Rental (BOM)'!$B$10:$B$104,Pricing!B12,'Rental (BOM)'!$K$10:$M$104)*$H$5 | I12: =SUMIF('Rental (BOM)'!$B$10:$B$104,Pricing!B12,'Rental (BOM)'!$M$10:$M$104)*$I$5
B13: Install Misc Goods | D13: =SUM(E13,F13,G13,H13,I13) | E13: =SUMIF('Rental (BOM)'!$B$10:$B$104,Pricing!B13,'Rental (BOM)'!$E$10:$E$104)*$E$5 | F13: =SUMIF('Rental (BOM)'!$B$10:$B$104,Pricing!B13,'Rental (BOM)'!$G$10:$G$104)*$F$5 | G13: =SUMIF('Rental (BOM)'!$B$10:$B$104,Pricing!B13,'Rental (BOM)'!$I$10:$I$104)*$G$5 | H13: =SUMIF('Rental (BOM)'!$B$10:$B$104,Pricing!B13,'Rental (BOM)'!$K$10:$M$104)*$H$5 | I13: =SUMIF('Rental (BOM)'!$B$10:$B$104,Pricing!B13,'Rental (BOM)'!$M$10:$M$104)*$I$5
B14: RF Equipment | D14: =SUM(E14,F14,G14,H14,I14) | E14: =SUMIF('Rental (BOM)'!$B$10:$B$104,Pricing!B14,'Rental (BOM)'!$E$10:$E$104)*$E$5 | F14: =SUMIF('Rental (BOM)'!$B$10:$B$104,Pricing!B14,'Rental (BOM)'!$G$10:$G$104)*$F$5 | G14: =SUMIF('Rental (BOM)'!$B$10:$B$104,Pricing!B14,'Rental (BOM)'!$I$10:$I$104)*$G$5 | H14: =SUMIF('Rental (BOM)'!$B$10:$B$104,Pricing!B14,'Rental (BOM)'!$K$10:$M$104)*$H$5 | I14: =SUMIF('Rental (BOM)'!$B$10:$B$104,Pricing!B14,'Rental (BOM)'!$M$10:$M$104)*$I$5
B15: LEO VSAT Equipment | D15: =SUM(E15,F15,G15,H15,I15) | E15: =SUMIF('Rental (BOM)'!$B$10:$B$104,Pricing!B15,'Rental (BOM)'!$E$10:$E$104)*$E$5 | F15: =SUMIF('Rental (BOM)'!$B$10:$B$104,Pricing!B15,'Rental (BOM)'!$G$10:$G$104)*$F$5 | G15: =SUMIF('Rental (BOM)'!$B$10:$B$104,Pricing!B15,'Rental (BOM)'!$I$10:$I$104)*$G$5 | H15: =SUMIF('Rental (BOM)'!$B$10:$B$104,Pricing!B15,'Rental (BOM)'!$K$10:$M$104)*$H$5 | I15: =SUMIF('Rental (BOM)'!$B$10:$B$104,Pricing!B15,'Rental (BOM)'!$M$10:$M$104)*$I$5
B16: MEO VSAT Equipment | D16: =SUM(E16,F16,G16,H16,I16) | E16: =SUMIF('Rental (BOM)'!$B$10:$B$104,Pricing!B16,'Rental (BOM)'!$E$10:$E$104)*$E$5 | F16: =SUMIF('Rental (BOM)'!$B$10:$B$104,Pricing!B16,'Rental (BOM)'!$G$10:$G$104)*$F$5 | G16: =SUMIF('Rental (BOM)'!$B$10:$B$104,Pricing!B16,'Rental (BOM)'!$I$10:$I$104)*$G$5 | H16: =SUMIF('Rental (BOM)'!$B$10:$B$104,Pricing!B16,'Rental (BOM)'!$K$10:$M$104)*$H$5 | I16: =SUMIF('Rental (BOM)'!$B$10:$B$104,Pricing!B16,'Rental (BOM)'!$M$10:$M$104)*$I$5
B17: GEO VSAT Equipment | D17: =SUM(E17,F17,G17,H17,I17) | E17: =SUMIF('Rental (BOM)'!$B$10:$B$104,Pricing!B17,'Rental (BOM)'!$E$10:$E$104)*$E$5 | F17: =SUMIF('Rental (BOM)'!$B$10:$B$104,Pricing!B17,'Rental (BOM)'!$G$10:$G$104)*$F$5 | G17: =SUMIF('Rental (BOM)'!$B$10:$B$104,Pricing!B17,'Rental (BOM)'!$I$10:$I$104)*$G$5 | H17: =SUMIF('Rental (BOM)'!$B$10:$B$104,Pricing!B17,'Rental (BOM)'!$K$10:$M$104)*$H$5 | I17: =SUMIF('Rental (BOM)'!$B$10:$B$104,Pricing!B17,'Rental (BOM)'!$M$10:$M$104)*$I$5
B18: VSAT - GENERAL EQUIP (Modems, OBM, etc.) | D18: =SUM(E18,F18,G18,H18,I18) | E18: =SUMIF('Rental (BOM)'!$B$10:$B$104,Pricing!B18,'Rental (BOM)'!$E$10:$E$104)*$E$5 | F18: =SUMIF('Rental (BOM)'!$B$10:$B$104,Pricing!B18,'Rental (BOM)'!$G$10:$G$104)*$F$5 | G18: =SUMIF('Rental (BOM)'!$B$10:$B$104,Pricing!B18,'Rental (BOM)'!$I$10:$I$104)*$G$5 | H18: =SUMIF('Rental (BOM)'!$B$10:$B$104,Pricing!B18,'Rental (BOM)'!$K$10:$M$104)*$H$5 | I18: =SUMIF('Rental (BOM)'!$B$10:$B$104,Pricing!B18,'Rental (BOM)'!$M$10:$M$104)*$I$5
B19: Network Equipment | D19: =SUM(E19,F19,G19,H19,I19) | E19: =SUMIF('Rental (BOM)'!$B$10:$B$104,Pricing!B19,'Rental (BOM)'!$E$10:$E$104)*$E$5 | F19: =SUMIF('Rental (BOM)'!$B$10:$B$104,Pricing!B19,'Rental (BOM)'!$G$10:$G$104)*$F$5 | G19: =SUMIF('Rental (BOM)'!$B$10:$B$104,Pricing!B19,'Rental (BOM)'!$I$10:$I$104)*$G$5 | H19: =SUMIF('Rental (BOM)'!$B$10:$B$104,Pricing!B19,'Rental (BOM)'!$K$10:$M$104)*$H$5 | I19: =SUMIF('Rental (BOM)'!$B$10:$B$104,Pricing!B19,'Rental (BOM)'!$M$10:$M$104)*$I$5
B20: Phones & Intercoms | D20: =SUM(E20,F20,G20,H20,I20) | E20: =SUMIF('Rental (BOM)'!$B$10:$B$104,Pricing!B20,'Rental (BOM)'!$E$10:$E$104)*$E$5 | F20: =SUMIF('Rental (BOM)'!$B$10:$B$104,Pricing!B20,'Rental (BOM)'!$G$10:$G$104)*$F$5 | G20: =SUMIF('Rental (BOM)'!$B$10:$B$104,Pricing!B20,'Rental (BOM)'!$I$10:$I$104)*$G$5 | H20: =SUMIF('Rental (BOM)'!$B$10:$B$104,Pricing!B20,'Rental (BOM)'!$K$10:$M$104)*$H$5 | I20: =SUMIF('Rental (BOM)'!$B$10:$B$104,Pricing!B20,'Rental (BOM)'!$M$10:$M$104)*$I$5
B21: SCADA Equipment | D21: =SUM(E21,F21,G21,H21,I21) | E21: =SUMIF('Rental (BOM)'!$B$10:$B$104,Pricing!B21,'Rental (BOM)'!$E$10:$E$104)*$E$5 | F21: =SUMIF('Rental (BOM)'!$B$10:$B$104,Pricing!B21,'Rental (BOM)'!$G$10:$G$104)*$F$5 | G21: =SUMIF('Rental (BOM)'!$B$10:$B$104,Pricing!B21,'Rental (BOM)'!$I$10:$I$104)*$G$5 | H21: =SUMIF('Rental (BOM)'!$B$10:$B$104,Pricing!B21,'Rental (BOM)'!$K$10:$M$104)*$H$5 | I21: =SUMIF('Rental (BOM)'!$B$10:$B$104,Pricing!B21,'Rental (BOM)'!$M$10:$M$104)*$I$5
B22: Other | D22: =SUM(E22,F22,G22,H22,I22) | E22: =SUMIF('Rental (BOM)'!$B$10:$B$104,Pricing!B22,'Rental (BOM)'!$E$10:$E$104)*$E$5 | F22: =SUMIF('Rental (BOM)'!$B$10:$B$104,Pricing!B22,'Rental (BOM)'!$G$10:$G$104)*$F$5 | G22: =SUMIF('Rental (BOM)'!$B$10:$B$104,Pricing!B22,'Rental (BOM)'!$I$10:$I$104)*$G$5 | H22: =SUMIF('Rental (BOM)'!$B$10:$B$104,Pricing!B22,'Rental (BOM)'!$K$10:$M$104)*$H$5 | I22: =SUMIF('Rental (BOM)'!$B$10:$B$104,Pricing!B22,'Rental (BOM)'!$M$10:$M$104)*$I$5
B23: -
B24: Labor Cost | D24: =SUM(D25:D36) | E24: =SUM(E25:E36) | F24: =SUM(F25:F36) | G24: =SUM(G25:G36) | H24: =SUM(H25:H36) | I24: =SUM(I25:I36)
B25: Project Management | D25: =SUM(E25,F25,G25,H25,I25) | E25: =SUMIF('Rental (BOM)'!$B$106:$B$126,Pricing!B25,'Rental (BOM)'!$E$106:$E$126)*$E$5 | F25: =SUMIF('Rental (BOM)'!$B$106:$B$126,Pricing!B25,'Rental (BOM)'!$G$106:$G$126)*$F$5 | G25: =SUMIF('Rental (BOM)'!$B$106:$B$126,Pricing!B25,'Rental (BOM)'!$I$106:$I$126)*$G$5 | H25: =SUMIF('Rental (BOM)'!$B$106:$B$126,Pricing!B25,'Rental (BOM)'!$K$106:$K$126)*$H$5 | I25: =SUMIF('Rental (BOM)'!$B$106:$B$126,Pricing!B25,'Rental (BOM)'!$M$106:$M$126)*$I$5
B26: Engineering | D26: =SUM(E26,F26,G26,H26,I26) | E26: =SUMIF('Rental (BOM)'!$B$106:$B$126,Pricing!B26,'Rental (BOM)'!$E$106:$E$126)*$E$5 | F26: =SUMIF('Rental (BOM)'!$B$106:$B$126,Pricing!B26,'Rental (BOM)'!$G$106:$G$126)*$F$5 | G26: =SUMIF('Rental (BOM)'!$B$106:$B$126,Pricing!B26,'Rental (BOM)'!$I$106:$I$126)*$G$5 | H26: =SUMIF('Rental (BOM)'!$B$106:$B$126,Pricing!B26,'Rental (BOM)'!$K$106:$K$126)*$H$5 | I26: =SUMIF('Rental (BOM)'!$B$106:$B$126,Pricing!B26,'Rental (BOM)'!$M$106:$M$126)*$I$5
B27: Field Installation | D27: =SUM(E27,F27,G27,H27,I27) | E27: =SUMIF('Rental (BOM)'!$B$106:$B$126,Pricing!B27,'Rental (BOM)'!$E$106:$E$126)*$E$5 | F27: =SUMIF('Rental (BOM)'!$B$106:$B$126,Pricing!B27,'Rental (BOM)'!$G$106:$G$126)*$F$5 | G27: =SUMIF('Rental (BOM)'!$B$106:$B$126,Pricing!B27,'Rental (BOM)'!$I$106:$I$126)*$G$5 | H27: =SUMIF('Rental (BOM)'!$B$106:$B$126,Pricing!B27,'Rental (BOM)'!$K$106:$K$126)*$H$5 | I27: =SUMIF('Rental (BOM)'!$B$106:$B$126,Pricing!B27,'Rental (BOM)'!$M$106:$M$126)*$I$5
B28: Labor - Admin | D28: =SUM(E28,F28,G28,H28,I28) | E28: =SUMIF('Rental (BOM)'!$B$106:$B$126,Pricing!B28,'Rental (BOM)'!$E$106:$E$126)*$E$5 | F28: =SUMIF('Rental (BOM)'!$B$106:$B$126,Pricing!B28,'Rental (BOM)'!$G$106:$G$126)*$F$5 | G28: =SUMIF('Rental (BOM)'!$B$106:$B$126,Pricing!B28,'Rental (BOM)'!$I$106:$I$126)*$G$5 | H28: =SUMIF('Rental (BOM)'!$B$106:$B$126,Pricing!B28,'Rental (BOM)'!$K$106:$K$126)*$H$5 | I28: =SUMIF('Rental (BOM)'!$B$106:$B$126,Pricing!B28,'Rental (BOM)'!$M$106:$M$126)*$I$5
B29: Labor - Documentation | D29: =SUM(E29,F29,G29,H29,I29) | E29: =SUMIF('Rental (BOM)'!$B$106:$B$126,Pricing!B29,'Rental (BOM)'!$E$106:$E$126)*$E$5 | F29: =SUMIF('Rental (BOM)'!$B$106:$B$126,Pricing!B29,'Rental (BOM)'!$G$106:$G$126)*$F$5 | G29: =SUMIF('Rental (BOM)'!$B$106:$B$126,Pricing!B29,'Rental (BOM)'!$I$106:$I$126)*$G$5 | H29: =SUMIF('Rental (BOM)'!$B$106:$B$126,Pricing!B29,'Rental (BOM)'!$K$106:$K$126)*$H$5 | I29: =SUMIF('Rental (BOM)'!$B$106:$B$126,Pricing!B29,'Rental (BOM)'!$M$106:$M$126)*$I$5
B30: Contract Labor | D30: =SUM(E30,F30,G30,H30,I30) | E30: =SUMIF('Rental (BOM)'!$B$106:$B$126,Pricing!B30,'Rental (BOM)'!$E$106:$E$126)*$E$5 | F30: =SUMIF('Rental (BOM)'!$B$106:$B$126,Pricing!B30,'Rental (BOM)'!$G$106:$G$126)*$F$5 | G30: =SUMIF('Rental (BOM)'!$B$106:$B$126,Pricing!B30,'Rental (BOM)'!$I$106:$I$126)*$G$5 | H30: =SUMIF('Rental (BOM)'!$B$106:$B$126,Pricing!B30,'Rental (BOM)'!$K$106:$K$126)*$H$5 | I30: =SUMIF('Rental (BOM)'!$B$106:$B$126,Pricing!B30,'Rental (BOM)'!$M$106:$M$126)*$I$5
B31: Travel (Air, Uber, Parking, etc) | D31: =SUM(E31,F31,G31,H31,I31) | E31: =SUMIF('Rental (BOM)'!$B$106:$B$126,Pricing!B31,'Rental (BOM)'!$E$106:$E$126)*$E$5 | F31: =SUMIF('Rental (BOM)'!$B$106:$B$126,Pricing!B31,'Rental (BOM)'!$G$106:$G$126)*$F$5 | G31: =SUMIF('Rental (BOM)'!$B$106:$B$126,Pricing!B31,'Rental (BOM)'!$I$106:$I$126)*$G$5 | H31: =SUMIF('Rental (BOM)'!$B$106:$B$126,Pricing!B31,'Rental (BOM)'!$K$106:$K$126)*$H$5 | I31: =SUMIF('Rental (BOM)'!$B$106:$B$126,Pricing!B31,'Rental (BOM)'!$M$106:$M$126)*$I$5
B32: Freight and Shipping | D32: =SUM(E32,F32,G32,H32,I32) | E32: =SUMIF('Rental (BOM)'!$B$106:$B$126,Pricing!B32,'Rental (BOM)'!$E$106:$E$126)*$E$5 | F32: =SUMIF('Rental (BOM)'!$B$106:$B$126,Pricing!B32,'Rental (BOM)'!$G$106:$G$126)*$F$5 | G32: =SUMIF('Rental (BOM)'!$B$106:$B$126,Pricing!B32,'Rental (BOM)'!$I$106:$I$126)*$G$5 | H32: =SUMIF('Rental (BOM)'!$B$106:$B$126,Pricing!B32,'Rental (BOM)'!$K$106:$K$126)*$H$5 | I32: =SUMIF('Rental (BOM)'!$B$106:$B$126,Pricing!B32,'Rental (BOM)'!$M$106:$M$126)*$I$5
B33: Vehicle or Equipment Rental | D33: =SUM(E33,F33,G33,H33,I33) | E33: =SUMIF('Rental (BOM)'!$B$106:$B$126,Pricing!B33,'Rental (BOM)'!$E$106:$E$126)*$E$5 | F33: =SUMIF('Rental (BOM)'!$B$106:$B$126,Pricing!B33,'Rental (BOM)'!$G$106:$G$126)*$F$5 | G33: =SUMIF('Rental (BOM)'!$B$106:$B$126,Pricing!B33,'Rental (BOM)'!$I$106:$I$126)*$G$5 | H33: =SUMIF('Rental (BOM)'!$B$106:$B$126,Pricing!B33,'Rental (BOM)'!$K$106:$K$126)*$H$5 | I33: =SUMIF('Rental (BOM)'!$B$106:$B$126,Pricing!B33,'Rental (BOM)'!$M$106:$M$126)*$I$5
B34: Mileage | D34: =SUM(E34,F34,G34,H34,I34) | E34: =SUMIF('Rental (BOM)'!$B$106:$B$126,Pricing!B34,'Rental (BOM)'!$E$106:$E$126)*$E$5 | F34: =SUMIF('Rental (BOM)'!$B$106:$B$126,Pricing!B34,'Rental (BOM)'!$G$106:$G$126)*$F$5 | G34: =SUMIF('Rental (BOM)'!$B$106:$B$126,Pricing!B34,'Rental (BOM)'!$I$106:$I$126)*$G$5 | H34: =SUMIF('Rental (BOM)'!$B$106:$B$126,Pricing!B34,'Rental (BOM)'!$K$106:$K$126)*$H$5 | I34: =SUMIF('Rental (BOM)'!$B$106:$B$126,Pricing!B34,'Rental (BOM)'!$M$106:$M$126)*$I$5
B35: Hotel & Meals | D35: =SUM(E35,F35,G35,H35,I35) | E35: =SUMIF('Rental (BOM)'!$B$106:$B$126,Pricing!B35,'Rental (BOM)'!$E$106:$E$126)*$E$5 | F35: =SUMIF('Rental (BOM)'!$B$106:$B$126,Pricing!B35,'Rental (BOM)'!$G$106:$G$126)*$F$5 | G35: =SUMIF('Rental (BOM)'!$B$106:$B$126,Pricing!B35,'Rental (BOM)'!$I$106:$I$126)*$G$5 | H35: =SUMIF('Rental (BOM)'!$B$106:$B$126,Pricing!B35,'Rental (BOM)'!$K$106:$K$126)*$H$5 | I35: =SUMIF('Rental (BOM)'!$B$106:$B$126,Pricing!B35,'Rental (BOM)'!$M$106:$M$126)*$I$5
B36: Other | D36: =SUM(E36,F36,G36,H36,I36) | E36: =SUMIF('Rental (BOM)'!$B$106:$B$126,Pricing!B36,'Rental (BOM)'!$E$106:$E$126)*$E$5 | F36: =SUMIF('Rental (BOM)'!$B$106:$B$126,Pricing!B36,'Rental (BOM)'!$G$106:$G$126)*$F$5 | G36: =SUMIF('Rental (BOM)'!$B$106:$B$126,Pricing!B36,'Rental (BOM)'!$I$106:$I$126)*$G$5 | H36: =SUMIF('Rental (BOM)'!$B$106:$B$126,Pricing!B36,'Rental (BOM)'!$K$106:$K$126)*$H$5 | I36: =SUMIF('Rental (BOM)'!$B$106:$B$126,Pricing!B36,'Rental (BOM)'!$M$106:$M$126)*$I$5
B37: -
B38: Recurring Cost | D38: =SUM(D39:D44) | E38: =SUM(E39:E44) | F38: =SUM(F39:F44) | G38: =SUM(G39:G44) | H38: =SUM(H39:H44) | I38: =SUM(I39:I44)
B39: 3rd Party Services | D39: =SUM(E39,F39,G39,H39,I39) | E39: =SUMIF('Rental (BOM)'!$B$128:$B$150,Pricing!B39,'Rental (BOM)'!$E$128:$E$150)*$E$5 | F39: =SUMIF('Rental (BOM)'!$B$128:$B$150,Pricing!B39,'Rental (BOM)'!$G$128:$G$150)*$F$5 | G39: =SUMIF('Rental (BOM)'!$B$128:$B$150,Pricing!B39,'Rental (BOM)'!$I$128:$I$150)*$G$5 | H39: =SUMIF('Rental (BOM)'!$B$128:$B$150,Pricing!B39,'Rental (BOM)'!$K$128:$K$150)*$H$5 | I39: =SUMIF('Rental (BOM)'!$B$128:$B$150,Pricing!B39,'Rental (BOM)'!$M$128:$M$150)*$I$5
B40: Terrestrial Connectivity | D40: =SUM(E40,F40,G40,H40,I40) | E40: =SUMIF('Rental (BOM)'!$B$128:$B$150,Pricing!B40,'Rental (BOM)'!$E$128:$E$150)*$E$5 | F40: =SUMIF('Rental (BOM)'!$B$128:$B$150,Pricing!B40,'Rental (BOM)'!$G$128:$G$150)*$F$5 | G40: =SUMIF('Rental (BOM)'!$B$128:$B$150,Pricing!B40,'Rental (BOM)'!$I$128:$I$150)*$G$5 | H40: =SUMIF('Rental (BOM)'!$B$128:$B$150,Pricing!B40,'Rental (BOM)'!$K$128:$K$150)*$H$5 | I40: =SUMIF('Rental (BOM)'!$B$128:$B$150,Pricing!B40,'Rental (BOM)'!$M$128:$M$150)*$I$5
B41: LEO, MEO, GEO Subscription Recurring | D41: =SUM(E41,F41,G41,H41,I41) | E41: =SUMIF('Rental (BOM)'!$B$128:$B$150,Pricing!B41,'Rental (BOM)'!$E$128:$E$150)*$E$5 | F41: =SUMIF('Rental (BOM)'!$B$128:$B$150,Pricing!B41,'Rental (BOM)'!$G$128:$G$150)*$F$5 | G41: =SUMIF('Rental (BOM)'!$B$128:$B$150,Pricing!B41,'Rental (BOM)'!$I$128:$I$150)*$G$5 | H41: =SUMIF('Rental (BOM)'!$B$128:$B$150,Pricing!B41,'Rental (BOM)'!$K$128:$K$150)*$H$5 | I41: =SUMIF('Rental (BOM)'!$B$128:$B$150,Pricing!B41,'Rental (BOM)'!$M$128:$M$150)*$I$5
B42: Tower Rental | D42: =SUM(E42,F42,G42,H42,I42) | E42: =SUMIF('Rental (BOM)'!$B$128:$B$150,Pricing!B42,'Rental (BOM)'!$E$128:$E$150)*$E$5 | F42: =SUMIF('Rental (BOM)'!$B$128:$B$150,Pricing!B42,'Rental (BOM)'!$G$128:$G$150)*$F$5 | G42: =SUMIF('Rental (BOM)'!$B$128:$B$150,Pricing!B42,'Rental (BOM)'!$I$128:$I$150)*$G$5 | H42: =SUMIF('Rental (BOM)'!$B$128:$B$150,Pricing!B42,'Rental (BOM)'!$K$128:$K$150)*$H$5 | I42: =SUMIF('Rental (BOM)'!$B$128:$B$150,Pricing!B42,'Rental (BOM)'!$M$128:$M$150)*$I$5
B43: Cellular or Traditional Phone Plan | D43: =SUM(E43,F43,G43,H43,I43) | E43: =SUMIF('Rental (BOM)'!$B$128:$B$150,Pricing!B43,'Rental (BOM)'!$E$128:$E$150)*$E$5 | F43: =SUMIF('Rental (BOM)'!$B$128:$B$150,Pricing!B43,'Rental (BOM)'!$G$128:$G$150)*$F$5 | G43: =SUMIF('Rental (BOM)'!$B$128:$B$150,Pricing!B43,'Rental (BOM)'!$I$128:$I$150)*$G$5 | H43: =SUMIF('Rental (BOM)'!$B$128:$B$150,Pricing!B43,'Rental (BOM)'!$K$128:$K$150)*$H$5 | I43: =SUMIF('Rental (BOM)'!$B$128:$B$150,Pricing!B43,'Rental (BOM)'!$M$128:$M$150)*$I$5
B44: Other | D44: =SUM(E44,F44,G44,H44,I44) | E44: =SUMIF('Rental (BOM)'!$B$128:$B$150,Pricing!B44,'Rental (BOM)'!$E$128:$E$150)*$E$5 | F44: =SUMIF('Rental (BOM)'!$B$128:$B$150,Pricing!B44,'Rental (BOM)'!$G$128:$G$150)*$F$5 | G44: =SUMIF('Rental (BOM)'!$B$128:$B$150,Pricing!B44,'Rental (BOM)'!$I$128:$I$150)*$G$5 | H44: =SUMIF('Rental (BOM)'!$B$128:$B$150,Pricing!B44,'Rental (BOM)'!$K$128:$K$150)*$H$5 | I44: =SUMIF('Rental (BOM)'!$B$128:$B$150,Pricing!B44,'Rental (BOM)'!$M$128:$M$150)*$I$5
B45: -
L46: Notes / Comments / Assumptions
B47: *Contingency | D47: SUM | E47: 1 | F47: 2 | G47: 3 | H47: 4 | I47: 5
B48: Percentage | D48: 0 | E48: 0 | F48: 0 | G48: 0 | H48: 0 | I48: 0
B49: Value | D49: =SUM(E49:I49) | E49: =SUM(E11,E24)*E48 | F49: =SUM(F11,F24)*F48 | G49: =SUM(G11,G24)*G48 | H49: =SUM(H11,H24)*H48 | I49: =SUM(I11,I24)*I48
B51: Rental | D51: SUM | E51: 1 | F51: 2 | G51: 3 | H51: 4 | I51: 5
B52: Capex | D52: =SUM(E52,F52,G52,H52,I52) | E52: =SUM(E11,E24,E49) | F52: =SUM(F11,F24,F49) | G52: =SUM(G11,G24,G49) | H52: =SUM(H11,H24,H49) | I52: =SUM(I11,I24,I49)
B53: Operating Costs (Monthly) | D53: =SUM(E53,F53,G53,H53,I53) | E53: =SUM(E38) | F53: =SUM(F38) | G53: =SUM(G38) | H53: =SUM(H38) | I53: =SUM(I38)
B54: TCV | D54: =E54+F54+G54+H54+I54 | E54: =((E6*E5)*E4)+E7 | F54: =((F6*F5)*F4)+F7 | G54: =((G6*G5)*G4)+G7 | H54: =((H6*H5)*H4)+H7 | I54: =((I6*I5)*I4)+I7
B55: Monthly Rate | D55: =SUM(E55,F55,G55,H55,I55) | E55: =E6*E5 | F55: =F6*F5 | G55: =G6*G5 | H55: =H6*H5 | I55: =I6*I5
B56: Monthly Rental Gross Profit | D56: =SUM(E56,F56,G56,H56,I56) | E56: =SUM(E55-E53) | F56: =SUM(F55-F53) | G56: =SUM(G55-G53) | H56: =SUM(H55-H53) | I56: =SUM(I55-I53) | L56: Notes / Comments / Assumptions
B57: Monthly Rental Contribution Margin % | D57: =IFERROR(((D55-D53))/D55,0) | E57: =IFERROR(((E55-E53))/E55,0) | F57: =IFERROR(((F55-F53))/F55,0) | G57: =IFERROR(((G55-G53))/G55,0) | H57: =IFERROR(((H55-H53))/H55,0) | I57: =IFERROR(((I55-I53))/I55,0)
B58: NPV | D58: =SUM(E58:I58) | E58: ='NPV - IRR'!J7 | F58: ='NPV - IRR'!J22 | G58: ='NPV - IRR'!G48 | H58: ='NPV - IRR'!G63 | I58: ='NPV - IRR'!G78
B59: IRR | D59: n/m | E59: =IFERROR(('NPV - IRR'!J6),0) | F59: =IFERROR(('NPV - IRR'!J21),0) | G59: =IFERROR(('NPV - IRR'!J36),0) | H59: =IFERROR(('NPV - IRR'!J51),0) | I59: =IFERROR(('NPV - IRR'!J66),0)
B60: Payback Period in Months | D60: =IFERROR('Cashflow & Payback'!C23,0) | E60: ='Cashflow & Payback'!C48 | F60: ='Cashflow & Payback'!C74 | G60: ='Cashflow & Payback'!C100 | H60: ='Cashflow & Payback'!C126 | I60: ='Cashflow & Payback'!C152
B61: Cash Flow | D61: =E61+F61+G61+H61+I61 | E61: =E54-E53*E4-E52+E100 | F61: =F54-F53*F4-F52+F100 | G61: =G54-G53*G4-G52+G100 | H61: =H54-H53*H4-H52+H100 | I61: =I54-I53*I4-I52+I100
B63: Sale Items | E63: 1 | F63: 2 | G63: 3 | H63: 4 | I63: 5
B64: Option Description | D64: →
B65: Number of Packages (Same Configuration) | D65: → | E65: 0 | F65: 0 | G65: 0 | H65: 0 | I65: 0
B66: Each Package Sale Price | D66: → | E66: =SUM('Sale (BOM)'!H10:H28,'Sale (BOM)'!H30:H41,'Sale (BOM)'!H43:H52) | F66: =SUM('Sale (BOM)'!K10:K28,'Sale (BOM)'!K30:K41,'Sale (BOM)'!K43:K52) | G66: =SUM('Sale (BOM)'!N10:N28,'Sale (BOM)'!N30:N41,'Sale (BOM)'!N43:N52) | H66: =SUM('Sale (BOM)'!Q10:Q28,'Sale (BOM)'!Q30:Q41,'Sale (BOM)'!Q43:Q52) | I66: =SUM('Sale (BOM)'!T10:T28,'Sale (BOM)'!T30:T41,'Sale (BOM)'!T43:T52)
D68: Summary | E68: 1 | F68: 2 | G68: 3 | H68: 4 | I68: 5
B69: Total Hardware Cost | D69: =SUM(D70:D77) | E69: =SUM(E70:E77) | F69: =SUM(F70:F77) | G69: =SUM(G70:G77) | H69: =SUM(H70:H77) | I69: =SUM(I70:I77)
B70: Install Equipment | D70: =SUM(E70,F70,G70,H70,I70) | E70: =SUMIF('Sale (BOM)'!$B$10:$B$41,Pricing!B70,'Sale (BOM)'!$G$10:$G$41)*$E$65 | F70: =SUMIF('Sale (BOM)'!$B$10:$B$41,Pricing!B70,'Sale (BOM)'!$J$10:$J$41)*$F$65 | G70: =SUMIF('Sale (BOM)'!$B$10:$B$41,Pricing!B70,'Sale (BOM)'!$M$10:$M$41)*$G$65 | H70: =SUMIF('Sale (BOM)'!$B$10:$B$41,Pricing!B70,'Sale (BOM)'!$P$10:$P$41)*$H$65 | I70: =SUMIF('Sale (BOM)'!$B$10:$B$41,Pricing!B70,'Sale (BOM)'!$S$10:$S$41)*$I$65
B71: Install Other | D71: =SUM(E71,F71,G71,H71,I71) | E71: =SUMIF('Sale (BOM)'!$B$10:$B$41,Pricing!B71,'Sale (BOM)'!$G$10:$G$41)*$E$65 | F71: =SUMIF('Sale (BOM)'!$B$10:$B$41,Pricing!B71,'Sale (BOM)'!$J$10:$J$41)*$F$65 | G71: =SUMIF('Sale (BOM)'!$B$10:$B$41,Pricing!B71,'Sale (BOM)'!$M$10:$M$41)*$G$65 | H71: =SUMIF('Sale (BOM)'!$B$10:$B$41,Pricing!B71,'Sale (BOM)'!$P$10:$P$41)*$H$65 | I71: =SUMIF('Sale (BOM)'!$B$10:$B$41,Pricing!B71,'Sale (BOM)'!$S$10:$S$41)*$I$65
B72: RF Equipment | D72: =SUM(E72,F72,G72,H72,I72) | E72: =SUMIF('Sale (BOM)'!$B$10:$B$41,Pricing!B72,'Sale (BOM)'!$G$10:$G$41)*$E$65 | F72: =SUMIF('Sale (BOM)'!$B$10:$B$41,Pricing!B72,'Sale (BOM)'!$J$10:$J$41)*$F$65 | G72: =SUMIF('Sale (BOM)'!$B$10:$B$41,Pricing!B72,'Sale (BOM)'!$M$10:$M$41)*$G$65 | H72: =SUMIF('Sale (BOM)'!$B$10:$B$41,Pricing!B72,'Sale (BOM)'!$P$10:$P$41)*$H$65 | I72: =SUMIF('Sale (BOM)'!$B$10:$B$41,Pricing!B72,'Sale (BOM)'!$S$10:$S$41)*$I$65
B73: VSAT Equipment | D73: =SUM(E73,F73,G73,H73,I73) | E73: =SUMIF('Sale (BOM)'!$B$10:$B$41,Pricing!B73,'Sale (BOM)'!$G$10:$G$41)*$E$65 | F73: =SUMIF('Sale (BOM)'!$B$10:$B$41,Pricing!B73,'Sale (BOM)'!$J$10:$J$41)*$F$65 | G73: =SUMIF('Sale (BOM)'!$B$10:$B$41,Pricing!B73,'Sale (BOM)'!$M$10:$M$41)*$G$65 | H73: =SUMIF('Sale (BOM)'!$B$10:$B$41,Pricing!B73,'Sale (BOM)'!$P$10:$P$41)*$H$65 | I73: =SUMIF('Sale (BOM)'!$B$10:$B$41,Pricing!B73,'Sale (BOM)'!$S$10:$S$41)*$I$65
B74: Network Equipment | D74: =SUM(E74,F74,G74,H74,I74) | E74: =SUMIF('Sale (BOM)'!$B$10:$B$41,Pricing!B74,'Sale (BOM)'!$G$10:$G$41)*$E$65 | F74: =SUMIF('Sale (BOM)'!$B$10:$B$41,Pricing!B74,'Sale (BOM)'!$J$10:$J$41)*$F$65 | G74: =SUMIF('Sale (BOM)'!$B$10:$B$41,Pricing!B74,'Sale (BOM)'!$M$10:$M$41)*$G$65 | H74: =SUMIF('Sale (BOM)'!$B$10:$B$41,Pricing!B74,'Sale (BOM)'!$P$10:$P$41)*$H$65 | I74: =SUMIF('Sale (BOM)'!$B$10:$B$41,Pricing!B74,'Sale (BOM)'!$S$10:$S$41)*$I$65
B75: Intercoms | D75: =SUM(E75,F75,G75,H75,I75) | E75: =SUMIF('Sale (BOM)'!$B$10:$B$41,Pricing!B75,'Sale (BOM)'!$G$10:$G$41)*$E$65 | F75: =SUMIF('Sale (BOM)'!$B$10:$B$41,Pricing!B75,'Sale (BOM)'!$J$10:$J$41)*$F$65 | G75: =SUMIF('Sale (BOM)'!$B$10:$B$41,Pricing!B75,'Sale (BOM)'!$M$10:$M$41)*$G$65 | H75: =SUMIF('Sale (BOM)'!$B$10:$B$41,Pricing!B75,'Sale (BOM)'!$P$10:$P$41)*$H$65 | I75: =SUMIF('Sale (BOM)'!$B$10:$B$41,Pricing!B75,'Sale (BOM)'!$S$10:$S$41)*$I$65
B76: SCADA Equipment | D76: =SUM(E76,F76,G76,H76,I76) | E76: =SUMIF('Sale (BOM)'!$B$10:$B$41,Pricing!B76,'Sale (BOM)'!$G$10:$G$41)*$E$65 | F76: =SUMIF('Sale (BOM)'!$B$10:$B$41,Pricing!B76,'Sale (BOM)'!$J$10:$J$41)*$F$65 | G76: =SUMIF('Sale (BOM)'!$B$10:$B$41,Pricing!B76,'Sale (BOM)'!$M$10:$M$41)*$G$65 | H76: =SUMIF('Sale (BOM)'!$B$10:$B$41,Pricing!B76,'Sale (BOM)'!$P$10:$P$41)*$H$65 | I76: =SUMIF('Sale (BOM)'!$B$10:$B$41,Pricing!B76,'Sale (BOM)'!$S$10:$S$41)*$I$65
B77: Other | D77: =SUM(E77,F77,G77,H77,I77) | E77: =SUMIF('Sale (BOM)'!$B$10:$B$41,Pricing!B77,'Sale (BOM)'!$G$10:$G$41)*$E$65 | F77: =SUMIF('Sale (BOM)'!$B$10:$B$41,Pricing!B77,'Sale (BOM)'!$J$10:$J$41)*$F$65 | G77: =SUMIF('Sale (BOM)'!$B$10:$B$41,Pricing!B77,'Sale (BOM)'!$M$10:$M$41)*$G$65 | H77: =SUMIF('Sale (BOM)'!$B$10:$B$41,Pricing!B77,'Sale (BOM)'!$P$10:$P$41)*$H$65 | I77: =SUMIF('Sale (BOM)'!$B$10:$B$41,Pricing!B77,'Sale (BOM)'!$S$10:$S$41)*$I$65
B78: Total Labor Cost | D78: =SUM(D79:D90) | E78: =SUM(E79:E90) | F78: =SUM(F79:F90) | G78: =SUM(G79:G90) | H78: =SUM(H79:H90) | I78: =SUM(I79:I90)
B79: Inst Labor Project Management | D79: =SUM(E79,F79,G79,H79,I79) | E79: =SUMIF('Sale (BOM)'!$B$43:$B$52,Pricing!B79,'Sale (BOM)'!$G$43:$G$52)*$E$65 | F79: =SUMIF('Sale (BOM)'!$B$43:$B$52,Pricing!B79,'Sale (BOM)'!$J$43:$J$52)*$F$65 | G79: =SUMIF('Sale (BOM)'!$B$43:$B$52,Pricing!B79,'Sale (BOM)'!$M$43:$M$52)*$G$65 | H79: =SUMIF('Sale (BOM)'!$B$43:$B$52,Pricing!B79,'Sale (BOM)'!$P$43:$P$52)*$H$65 | I79: =SUMIF('Sale (BOM)'!$B$43:$B$52,Pricing!B79,'Sale (BOM)'!$S$43:$S$52)*$I$65
B80: Inst Labor Engineering | D80: =SUM(E80,F80,G80,H80,I80) | E80: =SUMIF('Sale (BOM)'!$B$43:$B$52,Pricing!B80,'Sale (BOM)'!$G$43:$G$52)*$E$65 | F80: =SUMIF('Sale (BOM)'!$B$43:$B$52,Pricing!B80,'Sale (BOM)'!$J$43:$J$52)*$F$65 | G80: =SUMIF('Sale (BOM)'!$B$43:$B$52,Pricing!B80,'Sale (BOM)'!$M$43:$M$52)*$G$65 | H80: =SUMIF('Sale (BOM)'!$B$43:$B$52,Pricing!B80,'Sale (BOM)'!$P$43:$P$52)*$H$65 | I80: =SUMIF('Sale (BOM)'!$B$43:$B$52,Pricing!B80,'Sale (BOM)'!$S$43:$S$52)*$I$65
B81: Inst Labor Field Installation | D81: =SUM(E81,F81,G81,H81,I81) | E81: =SUMIF('Sale (BOM)'!$B$43:$B$52,Pricing!B81,'Sale (BOM)'!$G$43:$G$52)*$E$65 | F81: =SUMIF('Sale (BOM)'!$B$43:$B$52,Pricing!B81,'Sale (BOM)'!$J$43:$J$52)*$F$65 | G81: =SUMIF('Sale (BOM)'!$B$43:$B$52,Pricing!B81,'Sale (BOM)'!$M$43:$M$52)*$G$65 | H81: =SUMIF('Sale (BOM)'!$B$43:$B$52,Pricing!B81,'Sale (BOM)'!$P$43:$P$52)*$H$65 | I81: =SUMIF('Sale (BOM)'!$B$43:$B$52,Pricing!B81,'Sale (BOM)'!$S$43:$S$52)*$I$65
B82: Inst Labor Admin | D82: =SUM(E82,F82,G82,H82,I82) | E82: =SUMIF('Sale (BOM)'!$B$43:$B$52,Pricing!B82,'Sale (BOM)'!$G$43:$G$52)*$E$65 | F82: =SUMIF('Sale (BOM)'!$B$43:$B$52,Pricing!B82,'Sale (BOM)'!$J$43:$J$52)*$F$65 | G82: =SUMIF('Sale (BOM)'!$B$43:$B$52,Pricing!B82,'Sale (BOM)'!$M$43:$M$52)*$G$65 | H82: =SUMIF('Sale (BOM)'!$B$43:$B$52,Pricing!B82,'Sale (BOM)'!$P$43:$P$52)*$H$65 | I82: =SUMIF('Sale (BOM)'!$B$43:$B$52,Pricing!B82,'Sale (BOM)'!$S$43:$S$52)*$I$65
B83: Inst Labor Documentation | D83: =SUM(E83,F83,G83,H83,I83) | E83: =SUMIF('Sale (BOM)'!$B$43:$B$52,Pricing!B83,'Sale (BOM)'!$G$43:$G$52)*$E$65 | F83: =SUMIF('Sale (BOM)'!$B$43:$B$52,Pricing!B83,'Sale (BOM)'!$J$43:$J$52)*$F$65 | G83: =SUMIF('Sale (BOM)'!$B$43:$B$52,Pricing!B83,'Sale (BOM)'!$M$43:$M$52)*$G$65 | H83: =SUMIF('Sale (BOM)'!$B$43:$B$52,Pricing!B83,'Sale (BOM)'!$P$43:$P$52)*$H$65 | I83: =SUMIF('Sale (BOM)'!$B$43:$B$52,Pricing!B83,'Sale (BOM)'!$S$43:$S$52)*$I$65
B84: Inst Labor Contract Labor | D84: =SUM(E84,F84,G84,H84,I84) | E84: =SUMIF('Sale (BOM)'!$B$43:$B$52,Pricing!B84,'Sale (BOM)'!$G$43:$G$52)*$E$65 | F84: =SUMIF('Sale (BOM)'!$B$43:$B$52,Pricing!B84,'Sale (BOM)'!$J$43:$J$52)*$F$65 | G84: =SUMIF('Sale (BOM)'!$B$43:$B$52,Pricing!B84,'Sale (BOM)'!$M$43:$M$52)*$G$65 | H84: =SUMIF('Sale (BOM)'!$B$43:$B$52,Pricing!B84,'Sale (BOM)'!$P$43:$P$52)*$H$65 | I84: =SUMIF('Sale (BOM)'!$B$43:$B$52,Pricing!B84,'Sale (BOM)'!$S$43:$S$52)*$I$65
B85: Inst Other Travel | D85: =SUM(E85,F85,G85,H85,I85) | E85: =SUMIF('Sale (BOM)'!$B$43:$B$52,Pricing!B85,'Sale (BOM)'!$G$43:$G$52)*$E$65 | F85: =SUMIF('Sale (BOM)'!$B$43:$B$52,Pricing!B85,'Sale (BOM)'!$J$43:$J$52)*$F$65 | G85: =SUMIF('Sale (BOM)'!$B$43:$B$52,Pricing!B85,'Sale (BOM)'!$M$43:$M$52)*$G$65 | H85: =SUMIF('Sale (BOM)'!$B$43:$B$52,Pricing!B85,'Sale (BOM)'!$P$43:$P$52)*$H$65 | I85: =SUMIF('Sale (BOM)'!$B$43:$B$52,Pricing!B85,'Sale (BOM)'!$S$43:$S$52)*$I$65
B86: Inst Other Freight and Shipping | D86: =SUM(E86,F86,G86,H86,I86) | E86: =SUMIF('Sale (BOM)'!$B$43:$B$52,Pricing!B86,'Sale (BOM)'!$G$43:$G$52)*$E$65 | F86: =SUMIF('Sale (BOM)'!$B$43:$B$52,Pricing!B86,'Sale (BOM)'!$J$43:$J$52)*$F$65 | G86: =SUMIF('Sale (BOM)'!$B$43:$B$52,Pricing!B86,'Sale (BOM)'!$M$43:$M$52)*$G$65 | H86: =SUMIF('Sale (BOM)'!$B$43:$B$52,Pricing!B86,'Sale (BOM)'!$P$43:$P$52)*$H$65 | I86: =SUMIF('Sale (BOM)'!$B$43:$B$52,Pricing!B86,'Sale (BOM)'!$S$43:$S$52)*$I$65
B87: Inst Other Car Rental | D87: =SUM(E87,F87,G87,H87,I87) | E87: =SUMIF('Sale (BOM)'!$B$43:$B$52,Pricing!B87,'Sale (BOM)'!$G$43:$G$52)*$E$65 | F87: =SUMIF('Sale (BOM)'!$B$43:$B$52,Pricing!B87,'Sale (BOM)'!$J$43:$J$52)*$F$65 | G87: =SUMIF('Sale (BOM)'!$B$43:$B$52,Pricing!B87,'Sale (BOM)'!$M$43:$M$52)*$G$65 | H87: =SUMIF('Sale (BOM)'!$B$43:$B$52,Pricing!B87,'Sale (BOM)'!$P$43:$P$52)*$H$65 | I87: =SUMIF('Sale (BOM)'!$B$43:$B$52,Pricing!B87,'Sale (BOM)'!$S$43:$S$52)*$I$65
B88: Inst Other Hotel | D88: =SUM(E88,F88,G88,H88,I88) | E88: =SUMIF('Sale (BOM)'!$B$43:$B$52,Pricing!B88,'Sale (BOM)'!$G$43:$G$52)*$E$65 | F88: =SUMIF('Sale (BOM)'!$B$43:$B$52,Pricing!B88,'Sale (BOM)'!$J$43:$J$52)*$F$65 | G88: =SUMIF('Sale (BOM)'!$B$43:$B$52,Pricing!B88,'Sale (BOM)'!$M$43:$M$52)*$G$65 | H88: =SUMIF('Sale (BOM)'!$B$43:$B$52,Pricing!B88,'Sale (BOM)'!$P$43:$P$52)*$H$65 | I88: =SUMIF('Sale (BOM)'!$B$43:$B$52,Pricing!B88,'Sale (BOM)'!$S$43:$S$52)*$I$65
B89: Inst Other Meals | D89: =SUM(E89,F89,G89,H89,I89) | E89: =SUMIF('Sale (BOM)'!$B$43:$B$52,Pricing!B89,'Sale (BOM)'!$G$43:$G$52)*$E$65 | F89: =SUMIF('Sale (BOM)'!$B$43:$B$52,Pricing!B89,'Sale (BOM)'!$J$43:$J$52)*$F$65 | G89: =SUMIF('Sale (BOM)'!$B$43:$B$52,Pricing!B89,'Sale (BOM)'!$M$43:$M$52)*$G$65 | H89: =SUMIF('Sale (BOM)'!$B$43:$B$52,Pricing!B89,'Sale (BOM)'!$P$43:$P$52)*$H$65 | I89: =SUMIF('Sale (BOM)'!$B$43:$B$52,Pricing!B89,'Sale (BOM)'!$S$43:$S$52)*$I$65
B90: Other | D90: =SUM(E90,F90,G90,H90,I90) | E90: =SUMIF('Sale (BOM)'!$B$43:$B$52,Pricing!B90,'Sale (BOM)'!$G$43:$G$52)*$E$65 | F90: =SUMIF('Sale (BOM)'!$B$43:$B$52,Pricing!B90,'Sale (BOM)'!$J$43:$J$52)*$F$65 | G90: =SUMIF('Sale (BOM)'!$B$43:$B$52,Pricing!B90,'Sale (BOM)'!$M$43:$M$52)*$G$65 | H90: =SUMIF('Sale (BOM)'!$B$43:$B$52,Pricing!B90,'Sale (BOM)'!$P$43:$P$52)*$H$65 | I90: =SUMIF('Sale (BOM)'!$B$43:$B$52,Pricing!B90,'Sale (BOM)'!$S$43:$S$52)*$I$65
B92: Contingency | D92: SUM | E92: 1 | F92: 2 | G92: 3 | H92: 4 | I92: 5
B93: Percentage | D93: =IFERROR(AVERAGEIF(E93:I93,">0"),0) | E93: 0 | F93: 0 | G93: 0 | H93: 0 | I93: 0
B94: Value | D94: =SUM(E94:I94) | E94: =SUM(E69,E78)*E93 | F94: =SUM(F69,F78)*F93 | G94: =SUM(G69,G78)*G93 | H94: =SUM(H69,H78)*H93 | I94: =SUM(I69,I78)*I93
B96: Purchase | D96: SUM | E96: 1 | F96: 2 | G96: 3 | H96: 4 | I96: 5 | L96: Notes / Comments / Assumptions
B97: Hardware Cost | D97: =SUM(E97:I97) | E97: =SUM(E69,E94) | F97: =SUM(F69,F94) | G97: =SUM(G69,G94) | H97: =SUM(H69,H94) | I97: =SUM(I69,I94)
B98: Labor Cost | D98: =SUM(E98:I98) | E98: =SUM(E78) | F98: =SUM(F78) | G98: =SUM(G78) | H98: =SUM(H78) | I98: =SUM(I78)
B99: Sale Price | D99: =SUM(E99:I99) | E99: =SUM(E65*E66) | F99: =SUM(F65*F66) | G99: =SUM(G65*G66) | H99: =SUM(H65*H66) | I99: =SUM(I65*I66)
B100: Sale Gross Profit | D100: =SUM(E100:I100) | E100: =SUM(E99-(E97+E98)) | F100: =SUM(F99-(F97+F98)) | G100: =SUM(G99-(G97+G98)) | H100: =SUM(H99-(H97+H98)) | I100: =SUM(I99-(I97+I98))
B101: Sale Gross Margin % | D101: =IFERROR((D99-(D97+D98))/D99,0) | E101: =IFERROR((E99-(E97+E98))/E99,0) | F101: =IFERROR((F99-(F97+F98))/F99,0) | G101: =IFERROR((G99-(G97+G98))/G99,0) | H101: =IFERROR((H99-(H97+H98))/H99,0) | I101: =IFERROR((I99-(I97+I98))/I99,0)

Sheet Cashflow & Payback
A1: Payback | C1: =Pricing!B1
B2: Summary Column | C2: 0 | D2: =C2+1 | E2: =D2+1 | F2: =E2+1 | G2: =F2+1 | H2: =G2+1 | I2: =H2+1 | J2: =I2+1 | K2: =J2+1 | ... BJ2: =BI2+1
B3: Monthly Gross Profit | D3: =SUM(Pricing!D56)
B6: Flat Rate Install | C6: =SUM('Pricing'!E7:I7)
B7: Initial investment | C7: ='Pricing'!D52-SUM('Pricing'!E7:I7)-'Pricing'!D100
B8: Cash flows | C8: =-C7 | D8: =IF(D$2<='Pricing'!E$4,'Pricing'!E$56,0)+IF(D$2<='Pricing'!F$4,'Pricing'!F$56,0)+IF(D$2<='Pricing'!G$4,'Pricing'!G$56,0)+IF(D$2<='Pricing'!H$4,'Pricing'!H$56,0)+IF(D$2<='Pricing'!I$4,'Pricing'!I$56,0) | E8: =IF(E$2<='Pricing'!E$4,'Pricing'!E$56,0)+IF(E$2<='Pricing'!F$4,'Pricing'!F$56,0)+IF(E$2<='Pricing'!G$4,'Pricing'!G$56,0)+IF(E$2<='Pricing'!H$4,'Pricing'!H$56,0)+IF(E$2<='Pricing'!I$4,'Pricing'!I$56,0) | F8: =IF(F$2<='Pricing'!E$4,'Pricing'!E$56,0)+IF(F$2<='Pricing'!F$4,'Pricing'!F$56,0)+IF(F$2<='Pricing'!G$4,'Pricing'!G$56,0)+IF(F$2<='Pricing'!H$4,'Pricing'!H$56,0)+IF(F$2<='Pricing'!I$4,'Pricing'!I$56,0) | G8: =IF(G$2<='Pricing'!E$4,'Pricing'!E$56,0)+IF(G$2<='Pricing'!F$4,'Pricing'!F$56,0)+IF(G$2<='Pricing'!G$4,'Pricing'!G$56,0)+IF(G$2<='Pricing'!H$4,'Pricing'!H$56,0)+IF(G$2<='Pricing'!I$4,'Pricing'!I$56,0) | H8: =IF(H$2<='Pricing'!E$4,'Pricing'!E$56,0)+IF(H$2<='Pricing'!F$4,'Pricing'!F$56,0)+IF(H$2<='Pricing'!G$4,'Pricing'!G$56,0)+IF(H$2<='Pricing'!H$4,'Pricing'!H$56,0)+IF(H$2<='Pricing'!I$4,'Pricing'!I$56,0) | I8: =IF(I$2<='Pricing'!E$4,'Pricing'!E$56,0)+IF(I$2<='Pricing'!F$4,'Pricing'!F$56,0)+IF(I$2<='Pricing'!G$4,'Pricing'!G$56,0)+IF(I$2<='Pricing'!H$4,'Pricing'!H$56,0)+IF(I$2<='Pricing'!I$4,'Pricing'!I$56,0) | J8: =IF(J$2<='Pricing'!E$4,'Pricing'!E$56,0)+IF(J$2<='Pricing'!F$4,'Pricing'!F$56,0)+IF(J$2<='Pricing'!G$4,'Pricing'!G$56,0)+IF(J$2<='Pricing'!H$4,'Pricing'!H$56,0)+IF(J$2<='Pricing'!I$4,'Pricing'!I$56,0) | K8: =IF(K$2<='Pricing'!E$4,'Pricing'!E$56,0)+IF(K$2<='Pricing'!F$4,'Pricing'!F$56,0)+IF(K$2<='Pricing'!G$4,'Pricing'!G$56,0)+IF(K$2<='Pricing'!H$4,'Pricing'!H$56,0)+IF(K$2<='Pricing'!I$4,'Pricing'!I$56,0) | L8: =IF(L$2<='Pricing'!E$4,'Pricing'!E$56,0)+IF(L$2<='Pricing'!F$4,'Pricing'!F$56,0)+IF(L$2<='Pricing'!G$4,'Pricing'!G$56,0)+IF(L$2<='Pricing'!H$4,'Pricing'!H$56,0)+IF(L$2<='Pricing'!I$4,'Pricing'!I$56,0) | M8: =IF(M$2<='Pricing'!E$4,'Pricing'!E$56,0)+IF(M$2<='Pricing'!F$4,'Pricing'!F$56,0)+IF(M$2<='Pricing'!G$4,'Pricing'!G$56,0)+IF(M$2<='Pricing'!H$4,'Pricing'!H$56,0)+IF(M$2<='Pricing'!I$4,'Pricing'!I$56,0) | N8: =IF(N$2<='Pricing'!E$4,'Pricing'!E$56,0)+IF(N$2<='Pricing'!F$4,'Pricing'!F$56,0)+IF(N$2<='Pricing'!G$4,'Pricing'!G$56,0)+IF(N$2<='Pricing'!H$4,'Pricing'!H$56,0)+IF(N$2<='Pricing'!I$4,'Pricing'!I$56,0) | O8: =IF(O$2<='Pricing'!E$4,'Pricing'!E$56,0)+IF(O$2<='Pricing'!F$4,'Pricing'!F$56,0)+IF(O$2<='Pricing'!G$4,'Pricing'!G$56,0)+IF(O$2<='Pricing'!H$4,'Pricing'!H$56,0)+IF(O$2<='Pricing'!I$4,'Pricing'!I$56,0) | P8: =IF(P$2<='Pricing'!E$4,'Pricing'!E$56,0)+IF(P$2<='Pricing'!F$4,'Pricing'!F$56,0)+IF(P$2<='Pricing'!G$4,'Pricing'!G$56,0)+IF(P$2<='Pricing'!H$4,'Pricing'!H$56,0)+IF(P$2<='Pricing'!I$4,'Pricing'!I$56,0) | Q8: =IF(Q$2<='Pricing'!E$4,'Pricing'!E$56,0)+IF(Q$2<='Pricing'!F$4,'Pricing'!F$56,0)+IF(Q$2<='Pricing'!G$4,'Pricing'!G$56,0)+IF(Q$2<='Pricing'!H$4,'Pricing'!H$56,0)+IF(Q$2<='Pricing'!I$4,'Pricing'!I$56,0) | R8: =IF(R$2<='Pricing'!E$4,'Pricing'!E$56,0)+IF(R$2<='Pricing'!F$4,'Pricing'!F$56,0)+IF(R$2<='Pricing'!G$4,'Pricing'!G$56,0)+IF(R$2<='Pricing'!H$4,'Pricing'!H$56,0)+IF(R$2<='Pricing'!I$4,'Pricing'!I$56,0) | S8: =IF(S$2<='Pricing'!E$4,'Pricing'!E$56,0)+IF(S$2<='Pricing'!F$4,'Pricing'!F$56,0)+IF(S$2<='Pricing'!G$4,'Pricing'!G$56,0)+IF(S$2<='Pricing'!H$4,'Pricing'!H$56,0)+IF(S$2<='Pricing'!I$4,'Pricing'!I$56,0) | T8: =IF(T$2<='Pricing'!E$4,'Pricing'!E$56,0)+IF(T$2<='Pricing'!F$4,'Pricing'!F$56,0)+IF(T$2<='Pricing'!G$4,'Pricing'!G$56,0)+IF(T$2<='Pricing'!H$4,'Pricing'!H$56,0)+IF(T$2<='Pricing'!I$4,'Pricing'!I$56,0) | U8: =IF(U$2<='Pricing'!E$4,'Pricing'!E$56,0)+IF(U$2<='Pricing'!F$4,'Pricing'!F$56,0)+IF(U$2<='Pricing'!G$4,'Pricing'!G$56,0)+IF(U$2<='Pricing'!H$4,'Pricing'!H$56,0)+IF(U$2<='Pricing'!I$4,'Pricing'!I$56,0) | V8: =IF(V$2<='Pricing'!E$4,'Pricing'!E$56,0)+IF(V$2<='Pricing'!F$4,'Pricing'!F$56,0)+IF(V$2<='Pricing'!G$4,'Pricing'!G$56,0)+IF(V$2<='Pricing'!H$4,'Pricing'!H$56,0)+IF(V$2<='Pricing'!I$4,'Pricing'!I$56,0) | W8: =IF(W$2<='Pricing'!E$4,'Pricing'!E$56,0)+IF(W$2<='Pricing'!F$4,'Pricing'!F$56,0)+IF(W$2<='Pricing'!G$4,'Pricing'!G$56,0)+IF(W$2<='Pricing'!H$4,'Pricing'!H$56,0)+IF(W$2<='Pricing'!I$4,'Pricing'!I$56,0) | X8: =IF(X$2<='Pricing'!E$4,'Pricing'!E$56,0)+IF(X$2<='Pricing'!F$4,'Pricing'!F$56,0)+IF(X$2<='Pricing'!G$4,'Pricing'!G$56,0)+IF(X$2<='Pricing'!H$4,'Pricing'!H$56,0)+IF(X$2<='Pricing'!I$4,'Pricing'!I$56,0) | Y8: =IF(Y$2<='Pricing'!E$4,'Pricing'!E$56,0)+IF(Y$2<='Pricing'!F$4,'Pricing'!F$56,0)+IF(Y$2<='Pricing'!G$4,'Pricing'!G$56,0)+IF(Y$2<='Pricing'!H$4,'Pricing'!H$56,0)+IF(Y$2<='Pricing'!I$4,'Pricing'!I$56,0) | Z8: =IF(Z$2<='Pricing'!E$4,'Pricing'!E$56,0)+IF(Z$2<='Pricing'!F$4,'Pricing'!F$56,0)+IF(Z$2<='Pricing'!G$4,'Pricing'!G$56,0)+IF(Z$2<='Pricing'!H$4,'Pricing'!H$56,0)+IF(Z$2<='Pricing'!I$4,'Pricing'!I$56,0) | AA8: =IF(AA$2<='Pricing'!E$4,'Pricing'!E$56,0)+IF(AA$2<='Pricing'!F$4,'Pricing'!F$56,0)+IF(AA$2<='Pricing'!G$4,'Pricing'!G$56,0)+IF(AA$2<='Pricing'!H$4,'Pricing'!H$56,0)+IF(AA$2<='Pricing'!I$4,'Pricing'!I$56,0) | AB8: =IF(AB$2<='Pricing'!E$4,'Pricing'!E$56,0)+IF(AB$2<='Pricing'!F$4,'Pricing'!F$56,0)+IF(AB$2<='Pricing'!G$4,'Pricing'!G$56,0)+IF(AB$2<='Pricing'!H$4,'Pricing'!H$56,0)+IF(AB$2<='Pricing'!I$4,'Pricing'!I$56,0) | AC8: =IF(AC$2<='Pricing'!E$4,'Pricing'!E$56,0)+IF(AC$2<='Pricing'!F$4,'Pricing'!F$56,0)+IF(AC$2<='Pricing'!G$4,'Pricing'!G$56,0)+IF(AC$2<='Pricing'!H$4,'Pricing'!H$56,0)+IF(AC$2<='Pricing'!I$4,'Pricing'!I$56,0) | AD8: =IF(AD$2<='Pricing'!E$4,'Pricing'!E$56,0)+IF(AD$2<='Pricing'!F$4,'Pricing'!F$56,0)+IF(AD$2<='Pricing'!G$4,'Pricing'!G$56,0)+IF(AD$2<='Pricing'!H$4,'Pricing'!H$56,0)+IF(AD$2<='Pricing'!I$4,'Pricing'!I$56,0) | AE8: =IF(AE$2<='Pricing'!E$4,'Pricing'!E$56,0)+IF(AE$2<='Pricing'!F$4,'Pricing'!F$56,0)+IF(AE$2<='Pricing'!G$4,'Pricing'!G$56,0)+IF(AE$2<='Pricing'!H$4,'Pricing'!H$56,0)+IF(AE$2<='Pricing'!I$4,'Pricing'!I$56,0) | AF8: =IF(AF$2<='Pricing'!E$4,'Pricing'!E$56,0)+IF(AF$2<='Pricing'!F$4,'Pricing'!F$56,0)+IF(AF$2<='Pricing'!G$4,'Pricing'!G$56,0)+IF(AF$2<='Pricing'!H$4,'Pricing'!H$56,0)+IF(AF$2<='Pricing'!I$4,'Pricing'!I$56,0) | AG8: =IF(AG$2<='Pricing'!E$4,'Pricing'!E$56,0)+IF(AG$2<='Pricing'!F$4,'Pricing'!F$56,0)+IF(AG$2<='Pricing'!G$4,'Pricing'!G$56,0)+IF(AG$2<='Pricing'!H$4,'Pricing'!H$56,0)+IF(AG$2<='Pricing'!I$4,'Pricing'!I$56,0) | AH8: =IF(AH$2<='Pricing'!E$4,'Pricing'!E$56,0)+IF(AH$2<='Pricing'!F$4,'Pricing'!F$56,0)+IF(AH$2<='Pricing'!G$4,'Pricing'!G$56,0)+IF(AH$2<='Pricing'!H$4,'Pricing'!H$56,0)+IF(AH$2<='Pricing'!I$4,'Pricing'!I$56,0) | AI8: =IF(AI$2<='Pricing'!E$4,'Pricing'!E$56,0)+IF(AI$2<='Pricing'!F$4,'Pricing'!F$56,0)+IF(AI$2<='Pricing'!G$4,'Pricing'!G$56,0)+IF(AI$2<='Pricing'!H$4,'Pricing'!H$56,0)+IF(AI$2<='Pricing'!I$4,'Pricing'!I$56,0) | AJ8: =IF(AJ$2<='Pricing'!E$4,'Pricing'!E$56,0)+IF(AJ$2<='Pricing'!F$4,'Pricing'!F$56,0)+IF(AJ$2<='Pricing'!G$4,'Pricing'!G$56,0)+IF(AJ$2<='Pricing'!H$4,'Pricing'!H$56,0)+IF(AJ$2<='Pricing'!I$4,'Pricing'!I$56,0) | AK8: =IF(AK$2<='Pricing'!E$4,'Pricing'!E$56,0)+IF(AK$2<='Pricing'!F$4,'Pricing'!F$56,0)+IF(AK$2<='Pricing'!G$4,'Pricing'!G$56,0)+IF(AK$2<='Pricing'!H$4,'Pricing'!H$56,0)+IF(AK$2<='Pricing'!I$4,'Pricing'!I$56,0) | AL8: =IF(AL$2<='Pricing'!E$4,'Pricing'!E$56,0)+IF(AL$2<='Pricing'!F$4,'Pricing'!F$56,0)+IF(AL$2<='Pricing'!G$4,'Pricing'!G$56,0)+IF(AL$2<='Pricing'!H$4,'Pricing'!H$56,0)+IF(AL$2<='Pricing'!I$4,'Pricing'!I$56,0) | AM8: =IF(AM$2<='Pricing'!E$4,'Pricing'!E$56,0)+IF(AM$2<='Pricing'!F$4,'Pricing'!F$56,0)+IF(AM$2<='Pricing'!G$4,'Pricing'!G$56,0)+IF(AM$2<='Pricing'!H$4,'Pricing'!H$56,0)+IF(AM$2<='Pricing'!I$4,'Pricing'!I$56,0) | AN8: =IF(AN$2<='Pricing'!E$4,'Pricing'!E$56,0)+IF(AN$2<='Pricing'!F$4,'Pricing'!F$56,0)+IF(AN$2<='Pricing'!G$4,'Pricing'!G$56,0)+IF(AN$2<='Pricing'!H$4,'Pricing'!H$56,0)+IF(AN$2<='Pricing'!I$4,'Pricing'!I$56,0) | AO8: =IF(AO$2<='Pricing'!E$4,'Pricing'!E$56,0)+IF(AO$2<='Pricing'!F$4,'Pricing'!F$56,0)+IF(AO$2<='Pricing'!G$4,'Pricing'!G$56,0)+IF(AO$2<='Pricing'!H$4,'Pricing'!H$56,0)+IF(AO$2<='Pricing'!I$4,'Pricing'!I$56,0) | AP8: =IF(AP$2<='Pricing'!E$4,'Pricing'!E$56,0)+IF(AP$2<='Pricing'!F$4,'Pricing'!F$56,0)+IF(AP$2<='Pricing'!G$4,'Pricing'!G$56,0)+IF(AP$2<='Pricing'!H$4,'Pricing'!H$56,0)+IF(AP$2<='Pricing'!I$4,'Pricing'!I$56,0) | AQ8: =IF(AQ$2<='Pricing'!E$4,'Pricing'!E$56,0)+IF(AQ$2<='Pricing'!F$4,'Pricing'!F$56,0)+IF(AQ$2<='Pricing'!G$4,'Pricing'!G$56,0)+IF(AQ$2<='Pricing'!H$4,'Pricing'!H$56,0)+IF(AQ$2<='Pricing'!I$4,'Pricing'!I$56,0) | AR8: =IF(AR$2<='Pricing'!E$4,'Pricing'!E$56,0)+IF(AR$2<='Pricing'!F$4,'Pricing'!F$56,0)+IF(AR$2<='Pricing'!G$4,'Pricing'!G$56,0)+IF(AR$2<='Pricing'!H$4,'Pricing'!H$56,0)+IF(AR$2<='Pricing'!I$4,'Pricing'!I$56,0) | AS8: =IF(AS$2<='Pricing'!E$4,'Pricing'!E$56,0)+IF(AS$2<='Pricing'!F$4,'Pricing'!F$56,0)+IF(AS$2<='Pricing'!G$4,'Pricing'!G$56,0)+IF(AS$2<='Pricing'!H$4,'Pricing'!H$56,0)+IF(AS$2<='Pricing'!I$4,'Pricing'!I$56,0) | AT8: =IF(AT$2<='Pricing'!E$4,'Pricing'!E$56,0)+IF(AT$2<='Pricing'!F$4,'Pricing'!F$56,0)+IF(AT$2<='Pricing'!G$4,'Pricing'!G$56,0)+IF(AT$2<='Pricing'!H$4,'Pricing'!H$56,0)+IF(AT$2<='Pricing'!I$4,'Pricing'!I$56,0) | AU8: =IF(AU$2<='Pricing'!E$4,'Pricing'!E$56,0)+IF(AU$2<='Pricing'!F$4,'Pricing'!F$56,0)+IF(AU$2<='Pricing'!G$4,'Pricing'!G$56,0)+IF(AU$2<='Pricing'!H$4,'Pricing'!H$56,0)+IF(AU$2<='Pricing'!I$4,'Pricing'!I$56,0) | AV8: =IF(AV$2<='Pricing'!E$4,'Pricing'!E$56,0)+IF(AV$2<='Pricing'!F$4,'Pricing'!F$56,0)+IF(AV$2<='Pricing'!G$4,'Pricing'!G$56,0)+IF(AV$2<='Pricing'!H$4,'Pricing'!H$56,0)+IF(AV$2<='Pricing'!I$4,'Pricing'!I$56,0) | AW8: =IF(AW$2<='Pricing'!E$4,'Pricing'!E$56,0)+IF(AW$2<='Pricing'!F$4,'Pricing'!F$56,0)+IF(AW$2<='Pricing'!G$4,'Pricing'!G$56,0)+IF(AW$2<='Pricing'!H$4,'Pricing'!H$56,0)+IF(AW$2<='Pricing'!I$4,'Pricing'!I$56,0) | AX8: =IF(AX$2<='Pricing'!E$4,'Pricing'!E$56,0)+IF(AX$2<='Pricing'!F$4,'Pricing'!F$56,0)+IF(AX$2<='Pricing'!G$4,'Pricing'!G$56,0)+IF(AX$2<='Pricing'!H$4,'Pricing'!H$56,0)+IF(AX$2<='Pricing'!I$4,'Pricing'!I$56,0) | AY8: =IF(AY$2<='Pricing'!E$4,'Pricing'!E$56,0)+IF(AY$2<='Pricing'!F$4,'Pricing'!F$56,0)+IF(AY$2<='Pricing'!G$4,'Pricing'!G$56,0)+IF(AY$2<='Pricing'!H$4,'Pricing'!H$56,0)+IF(AY$2<='Pricing'!I$4,'Pricing'!I$56,0) | AZ8: =IF(AZ$2<='Pricing'!E$4,'Pricing'!E$56,0)+IF(AZ$2<='Pricing'!F$4,'Pricing'!F$56,0)+IF(AZ$2<='Pricing'!G$4,'Pricing'!G$56,0)+IF(AZ$2<='Pricing'!H$4,'Pricing'!H$56,0)+IF(AZ$2<='Pricing'!I$4,'Pricing'!I$56,0) | BA8: =IF(BA$2<='Pricing'!E$4,'Pricing'!E$56,0)+IF(BA$2<='Pricing'!F$4,'Pricing'!F$56,0)+IF(BA$2<='Pricing'!G$4,'Pricing'!G$56,0)+IF(BA$2<='Pricing'!H$4,'Pricing'!H$56,0)+IF(BA$2<='Pricing'!I$4,'Pricing'!I$56,0) | BB8: =IF(BB$2<='Pricing'!E$4,'Pricing'!E$56,0)+IF(BB$2<='Pricing'!F$4,'Pricing'!F$56,0)+IF(BB$2<='Pricing'!G$4,'Pricing'!G$56,0)+IF(BB$2<='Pricing'!H$4,'Pricing'!H$56,0)+IF(BB$2<='Pricing'!I$4,'Pricing'!I$56,0) | BC8: =IF(BC$2<='Pricing'!E$4,'Pricing'!E$56,0)+IF(BC$2<='Pricing'!F$4,'Pricing'!F$56,0)+IF(BC$2<='Pricing'!G$4,'Pricing'!G$56,0)+IF(BC$2<='Pricing'!H$4,'Pricing'!H$56,0)+IF(BC$2<='Pricing'!I$4,'Pricing'!I$56,0) | BD8: =IF(BD$2<='Pricing'!E$4,'Pricing'!E$56,0)+IF(BD$2<='Pricing'!F$4,'Pricing'!F$56,0)+IF(BD$2<='Pricing'!G$4,'Pricing'!G$56,0)+IF(BD$2<='Pricing'!H$4,'Pricing'!H$56,0)+IF(BD$2<='Pricing'!I$4,'Pricing'!I$56,0) | BE8: =IF(BE$2<='Pricing'!E$4,'Pricing'!E$56,0)+IF(BE$2<='Pricing'!F$4,'Pricing'!F$56,0)+IF(BE$2<='Pricing'!G$4,'Pricing'!G$56,0)+IF(BE$2<='Pricing'!H$4,'Pricing'!H$56,0)+IF(BE$2<='Pricing'!I$4,'Pricing'!I$56,0) | BF8: =IF(BF$2<='Pricing'!E$4,'Pricing'!E$56,0)+IF(BF$2<='Pricing'!F$4,'Pricing'!F$56,0)+IF(BF$2<='Pricing'!G$4,'Pricing'!G$56,0)+IF(BF$2<='Pricing'!H$4,'Pricing'!H$56,0)+IF(BF$2<='Pricing'!I$4,'Pricing'!I$56,0) | BG8: =IF(BG$2<='Pricing'!E$4,'Pricing'!E$56,0)+IF(BG$2<='Pricing'!F$4,'Pricing'!F$56,0)+IF(BG$2<='Pricing'!G$4,'Pricing'!G$56,0)+IF(BG$2<='Pricing'!H$4,'Pricing'!H$56,0)+IF(BG$2<='Pricing'!I$4,'Pricing'!I$56,0) | BH8: =IF(BH$2<='Pricing'!E$4,'Pricing'!E$56,0)+IF(BH$2<='Pricing'!F$4,'Pricing'!F$56,0)+IF(BH$2<='Pricing'!G$4,'Pricing'!G$56,0)+IF(BH$2<='Pricing'!H$4,'Pricing'!H$56,0)+IF(BH$2<='Pricing'!I$4,'Pricing'!I$56,0) | BI8: =IF(BI$2<='Pricing'!E$4,'Pricing'!E$56,0)+IF(BI$2<='Pricing'!F$4,'Pricing'!F$56,0)+IF(BI$2<='Pricing'!G$4,'Pricing'!G$56,0)+IF(BI$2<='Pricing'!H$4,'Pricing'!H$56,0)+IF(BI$2<='Pricing'!I$4,'Pricing'!I$56,0) | BJ8: =IF(BJ$2<='Pricing'!E$4,'Pricing'!E$56,0)+IF(BJ$2<='Pricing'!F$4,'Pricing'!F$56,0)+IF(BJ$2<='Pricing'!G$4,'Pricing'!G$56,0)+IF(BJ$2<='Pricing'!H$4,'Pricing'!H$56,0)+IF(BJ$2<='Pricing'!I$4,'Pricing'!I$56,0)
B10: Cumulative cash flows | C10: =C8 | D10: =SUM($C8:D8) | E10: =SUM($C8:E8) | F10: =SUM($C8:F8) | G10: =SUM($C8:G8) | H10: =SUM($C8:H8) | I10: =SUM($C8:I8) | J10: =SUM($C8:J8) | K10: =SUM($C8:K8) | ... BJ10: =SUM($C8:BJ8)
D11: =IF(AND(C10<0,D10>=0,D8>0),-C10/D8,"n/m") | E11: =IF(AND(D10<0,E10>=0,E8>0),-D10/E8,"n/m") | F11: =IF(AND(E10<0,F10>=0,F8>0),-E10/F8,"n/m") | G11: =IF(AND(F10<0,G10>=0,G8>0),-F10/G8,"n/m") | H11: =IF(AND(G10<0,H10>=0,H8>0),-G10/H8,"n/m") | I11: =IF(AND(H10<0,I10>=0,I8>0),-H10/I8,"n/m") | J11: =IF(AND(I10<0,J10>=0,J8>0),-I10/J8,"n/m") | K11: =IF(AND(J10<0,K10>=0,K8>0),-J10/K8,"n/m") | ... BJ11: =IF(AND(BI10<0,BJ10>=0,BJ8>0),-BI10/BJ8,"n/m")
B14: Payback period | C14: =IF(C7<=0,0,IF(BJ10<0,"n/m",COUNTIF(D10:BJ10,"<0")+INDEX(D11:BJ11,1,COUNTIF(D10:BJ10,"<0")+1)))
B17: Breaking it down >
B18: The Integer | C18: =IF(ISNUMBER(C14),INT(C14),"n/m")
B19: The Fraction | C19: =IF(ISNUMBER(C14),MOD(C14,1),"n/m")
B22: Bonus: Payback period calculations in just one cell
B23: Payback period | C23: =C14
B27: Column 1 | C27: 0 | D27: =C27+1 | E27: =D27+1 | F27: =E27+1 | G27: =F27+1 | H27: =G27+1 | I27: =H27+1 | J27: =I27+1 | K27: =J27+1 | ... BJ27: =BI27+1
B28: Monthly Gross Profit | D28: =SUM(Pricing!E56)
B32: Initial investment | C32: ='Pricing'!E52-'Pricing'!E7-'Pricing'!E100
B33: Cash flows | C33: =-C32 | D33: =IF(D$27<='Pricing'!E$4,'Pricing'!E$56,0) | E33: =IF(E$27<='Pricing'!E$4,'Pricing'!E$56,0) | F33: =IF(F$27<='Pricing'!E$4,'Pricing'!E$56,0) | G33: =IF(G$27<='Pricing'!E$4,'Pricing'!E$56,0) | H33: =IF(H$27<='Pricing'!E$4,'Pricing'!E$56,0) | I33: =IF(I$27<='Pricing'!E$4,'Pricing'!E$56,0) | J33: =IF(J$27<='Pricing'!E$4,'Pricing'!E$56,0) | K33: =IF(K$27<='Pricing'!E$4,'Pricing'!E$56,0) | L33: =IF(L$27<='Pricing'!E$4,'Pricing'!E$56,0) | M33: =IF(M$27<='Pricing'!E$4,'Pricing'!E$56,0) | N33: =IF(N$27<='Pricing'!E$4,'Pricing'!E$56,0) | O33: =IF(O$27<='Pricing'!E$4,'Pricing'!E$56,0) | P33: =IF(P$27<='Pricing'!E$4,'Pricing'!E$56,0) | Q33: =IF(Q$27<='Pricing'!E$4,'Pricing'!E$56,0) | R33: =IF(R$27<='Pricing'!E$4,'Pricing'!E$56,0) | S33: =IF(S$27<='Pricing'!E$4,'Pricing'!E$56,0) | T33: =IF(T$27<='Pricing'!E$4,'Pricing'!E$56,0) | U33: =IF(U$27<='Pricing'!E$4,'Pricing'!E$56,0) | V33: =IF(V$27<='Pricing'!E$4,'Pricing'!E$56,0) | W33: =IF(W$27<='Pricing'!E$4,'Pricing'!E$56,0) | X33: =IF(X$27<='Pricing'!E$4,'Pricing'!E$56,0) | Y33: =IF(Y$27<='Pricing'!E$4,'Pricing'!E$56,0) | Z33: =IF(Z$27<='Pricing'!E$4,'Pricing'!E$56,0) | AA33: =IF(AA$27<='Pricing'!E$4,'Pricing'!E$56,0) | AB33: =IF(AB$27<='Pricing'!E$4,'Pricing'!E$56,0) | AC33: =IF(AC$27<='Pricing'!E$4,'Pricing'!E$56,0) | AD33: =IF(AD$27<='Pricing'!E$4,'Pricing'!E$56,0) | AE33: =IF(AE$27<='Pricing'!E$4,'Pricing'!E$56,0) | AF33: =IF(AF$27<='Pricing'!E$4,'Pricing'!E$56,0) | AG33: =IF(AG$27<='Pricing'!E$4,'Pricing'!E$56,0) | AH33: =IF(AH$27<='Pricing'!E$4,'Pricing'!E$56,0) | AI33: =IF(AI$27<='Pricing'!E$4,'Pricing'!E$56,0) | AJ33: =IF(AJ$27<='Pricing'!E$4,'Pricing'!E$56,0) | AK33: =IF(AK$27<='Pricing'!E$4,'Pricing'!E$56,0) | AL33: =IF(AL$27<='Pricing'!E$4,'Pricing'!E$56,0) | AM33: =IF(AM$27<='Pricing'!E$4,'Pricing'!E$56,0) | AN33: =IF(AN$27<='Pricing'!E$4,'Pricing'!E$56,0) | AO33: =IF(AO$27<='Pricing'!E$4,'Pricing'!E$56,0) | AP33: =IF(AP$27<='Pricing'!E$4,'Pricing'!E$56,0) | AQ33: =IF(AQ$27<='Pricing'!E$4,'Pricing'!E$56,0) | AR33: =IF(AR$27<='Pricing'!E$4,'Pricing'!E$56,0) | AS33: =IF(AS$27<='Pricing'!E$4,'Pricing'!E$56,0) | AT33: =IF(AT$27<='Pricing'!E$4,'Pricing'!E$56,0) | AU33: =IF(AU$27<='Pricing'!E$4,'Pricing'!E$56,0) | AV33: =IF(AV$27<='Pricing'!E$4,'Pricing'!E$56,0) | AW33: =IF(AW$27<='Pricing'!E$4,'Pricing'!E$56,0) | AX33: =IF(AX$27<='Pricing'!E$4,'Pricing'!E$56,0) | AY33: =IF(AY$27<='Pricing'!E$4,'Pricing'!E$56,0) | AZ33: =IF(AZ$27<='Pricing'!E$4,'Pricing'!E$56,0) | BA33: =IF(BA$27<='Pricing'!E$4,'Pricing'!E$56,0) | BB33: =IF(BB$27<='Pricing'!E$4,'Pricing'!E$56,0) | BC33: =IF(BC$27<='Pricing'!E$4,'Pricing'!E$56,0) | BD33: =IF(BD$27<='Pricing'!E$4,'Pricing'!E$56,0) | BE33: =IF(BE$27<='Pricing'!E$4,'Pricing'!E$56,0) | BF33: =IF(BF$27<='Pricing'!E$4,'Pricing'!E$56,0) | BG33: =IF(BG$27<='Pricing'!E$4,'Pricing'!E$56,0) | BH33: =IF(BH$27<='Pricing'!E$4,'Pricing'!E$56,0) | BI33: =IF(BI$27<='Pricing'!E$4,'Pricing'!E$56,0) | BJ33: =IF(BJ$27<='Pricing'!E$4,'Pricing'!E$56,0)
B35: Cumulative cash flows | C35: =C33 | D35: =SUM($C33:D33) | E35: =SUM($C33:E33) | F35: =SUM($C33:F33) | G35: =SUM($C33:G33) | H35: =SUM($C33:H33) | I35: =SUM($C33:I33) | J35: =SUM($C33:J33) | K35: =SUM($C33:K33) | ... BJ35: =SUM($C33:BJ33)
D36: =IF(AND(C35<0,D35>=0,D33>0),-C35/D33,"n/m") | E36: =IF(AND(D35<0,E35>=0,E33>0),-D35/E33,"n/m") | F36: =IF(AND(E35<0,F35>=0,F33>0),-E35/F33,"n/m") | G36: =IF(AND(F35<0,G35>=0,G33>0),-F35/G33,"n/m") | H36: =IF(AND(G35<0,H35>=0,H33>0),-G35/H33,"n/m") | I36: =IF(AND(H35<0,I35>=0,I33>0),-H35/I33,"n/m") | J36: =IF(AND(I35<0,J35>=0,J33>0),-I35/J33,"n/m") | K36: =IF(AND(J35<0,K35>=0,K33>0),-J35/K33,"n/m") | ... BJ36: =IF(AND(BI35<0,BJ35>=0,BJ33>0),-BI35/BJ33,"n/m")
B39: Payback period | C39: =IF(C32<=0,0,IF(AND('Pricing'!E56>0,C32<='Pricing'!E56*'Pricing'!E4),C32/'Pricing'!E56,"n/m"))
B42: Breaking it down >
B43: The Integer | C43: =IF(ISNUMBER(C39),INT(C39),"n/m")
B44: The Fraction | C44: =IF(ISNUMBER(C39),MOD(C39,1),"n/m")
B47: Bonus: Payback period calculations in just one cell
B48: Payback period | C48: =C39
B53: Column 2 | C53: 0 | D53: =C53+1 | E53: =D53+1 | F53: =E53+1 | G53: =F53+1 | H53: =G53+1 | I53: =H53+1 | J53: =I53+1 | K53: =J53+1 | ... BJ53: =BI53+1
B54: Monthly Gross Profit | D54: =SUM(Pricing!F56)
B58: Initial investment | C58: ='Pricing'!F52-'Pricing'!F7-'Pricing'!F100
B59: Cash flows | C59: =-C58 | D59: =IF(D$53<='Pricing'!F$4,'Pricing'!F$56,0) | E59: =IF(E$53<='Pricing'!F$4,'Pricing'!F$56,0) | F59: =IF(F$53<='Pricing'!F$4,'Pricing'!F$56,0) | G59: =IF(G$53<='Pricing'!F$4,'Pricing'!F$56,0) | H59: =IF(H$53<='Pricing'!F$4,'Pricing'!F$56,0) | I59: =IF(I$53<='Pricing'!F$4,'Pricing'!F$56,0) | J59: =IF(J$53<='Pricing'!F$4,'Pricing'!F$56,0) | K59: =IF(K$53<='Pricing'!F$4,'Pricing'!F$56,0) | L59: =IF(L$53<='Pricing'!F$4,'Pricing'!F$56,0) | M59: =IF(M$53<='Pricing'!F$4,'Pricing'!F$56,0) | N59: =IF(N$53<='Pricing'!F$4,'Pricing'!F$56,0) | O59: =IF(O$53<='Pricing'!F$4,'Pricing'!F$56,0) | P59: =IF(P$53<='Pricing'!F$4,'Pricing'!F$56,0) | Q59: =IF(Q$53<='Pricing'!F$4,'Pricing'!F$56,0) | R59: =IF(R$53<='Pricing'!F$4,'Pricing'!F$56,0) | S59: =IF(S$53<='Pricing'!F$4,'Pricing'!F$56,0) | T59: =IF(T$53<='Pricing'!F$4,'Pricing'!F$56,0) | U59: =IF(U$53<='Pricing'!F$4,'Pricing'!F$56,0) | V59: =IF(V$53<='Pricing'!F$4,'Pricing'!F$56,0) | W59: =IF(W$53<='Pricing'!F$4,'Pricing'!F$56,0) | X59: =IF(X$53<='Pricing'!F$4,'Pricing'!F$56,0) | Y59: =IF(Y$53<='Pricing'!F$4,'Pricing'!F$56,0) | Z59: =IF(Z$53<='Pricing'!F$4,'Pricing'!F$56,0) | AA59: =IF(AA$53<='Pricing'!F$4,'Pricing'!F$56,0) | AB59: =IF(AB$53<='Pricing'!F$4,'Pricing'!F$56,0) | AC59: =IF(AC$53<='Pricing'!F$4,'Pricing'!F$56,0) | AD59: =IF(AD$53<='Pricing'!F$4,'Pricing'!F$56,0) | AE59: =IF(AE$53<='Pricing'!F$4,'Pricing'!F$56,0) | AF59: =IF(AF$53<='Pricing'!F$4,'Pricing'!F$56,0) | AG59: =IF(AG$53<='Pricing'!F$4,'Pricing'!F$56,0) | AH59: =IF(AH$53<='Pricing'!F$4,'Pricing'!F$56,0) | AI59: =IF(AI$53<='Pricing'!F$4,'Pricing'!F$56,0) | AJ59: =IF(AJ$53<='Pricing'!F$4,'Pricing'!F$56,0) | AK59: =IF(AK$53<='Pricing'!F$4,'Pricing'!F$56,0) | AL59: =IF(AL$53<='Pricing'!F$4,'Pricing'!F$56,0) | AM59: =IF(AM$53<='Pricing'!F$4,'Pricing'!F$56,0) | AN59: =IF(AN$53<='Pricing'!F$4,'Pricing'!F$56,0) | AO59: =IF(AO$53<='Pricing'!F$4,'Pricing'!F$56,0) | AP59: =IF(AP$53<='Pricing'!F$4,'Pricing'!F$56,0) | AQ59: =IF(AQ$53<='Pricing'!F$4,'Pricing'!F$56,0) | AR59: =IF(AR$53<='Pricing'!F$4,'Pricing'!F$56,0) | AS59: =IF(AS$53<='Pricing'!F$4,'Pricing'!F$56,0) | AT59: =IF(AT$53<='Pricing'!F$4,'Pricing'!F$56,0) | AU59: =IF(AU$53<='Pricing'!F$4,'Pricing'!F$56,0) | AV59: =IF(AV$53<='Pricing'!F$4,'Pricing'!F$56,0) | AW59: =IF(AW$53<='Pricing'!F$4,'Pricing'!F$56,0) | AX59: =IF(AX$53<='Pricing'!F$4,'Pricing'!F$56,0) | AY59: =IF(AY$53<='Pricing'!F$4,'Pricing'!F$56,0) | AZ59: =IF(AZ$53<='Pricing'!F$4,'Pricing'!F$56,0) | BA59: =IF(BA$53<='Pricing'!F$4,'Pricing'!F$56,0) | BB59: =IF(BB$53<='Pricing'!F$4,'Pricing'!F$56,0) | BC59: =IF(BC$53<='Pricing'!F$4,'Pricing'!F$56,0) | BD59: =IF(BD$53<='Pricing'!F$4,'Pricing'!F$56,0) | BE59: =IF(BE$53<='Pricing'!F$4,'Pricing'!F$56,0) | BF59: =IF(BF$53<='Pricing'!F$4,'Pricing'!F$56,0) | BG59: =IF(BG$53<='Pricing'!F$4,'Pricing'!F$56,0) | BH59: =IF(BH$53<='Pricing'!F$4,'Pricing'!F$56,0) | BI59: =IF(BI$53<='Pricing'!F$4,'Pricing'!F$56,0) | BJ59: =IF(BJ$53<='Pricing'!F$4,'Pricing'!F$56,0)
B61: Cumulative cash flows | C61: =C59 | D61: =SUM($C59:D59) | E61: =SUM($C59:E59) | F61: =SUM($C59:F59) | G61: =SUM($C59:G59) | H61: =SUM($C59:H59) | I61: =SUM($C59:I59) | J61: =SUM($C59:J59) | K61: =SUM($C59:K59) | ... BJ61: =SUM($C59:BJ59)
D62: =IF(AND(C61<0,D61>=0,D59>0),-C61/D59,"n/m") | E62: =IF(AND(D61<0,E61>=0,E59>0),-D61/E59,"n/m") | F62: =IF(AND(E61<0,F61>=0,F59>0),-E61/F59,"n/m") | G62: =IF(AND(F61<0,G61>=0,G59>0),-F61/G59,"n/m") | H62: =IF(AND(G61<0,H61>=0,H59>0),-G61/H59,"n/m") | I62: =IF(AND(H61<0,I61>=0,I59>0),-H61/I59,"n/m") | J62: =IF(AND(I61<0,J61>=0,J59>0),-I61/J59,"n/m") | K62: =IF(AND(J61<0,K61>=0,K59>0),-J61/K59,"n/m") | ... BJ62: =IF(AND(BI61<0,BJ61>=0,BJ59>0),-BI61/BJ59,"n/m")
B65: Payback period | C65: =IF(C58<=0,0,IF(AND('Pricing'!F56>0,C58<='Pricing'!F56*'Pricing'!F4),C58/'Pricing'!F56,"n/m"))
B68: Breaking it down >
B69: The Integer | C69: =IF(ISNUMBER(C65),INT(C65),"n/m")
B70: The Fraction | C70: =IF(ISNUMBER(C65),MOD(C65,1),"n/m")
B73: Bonus: Payback period calculations in just one cell
B74: Payback period | C74: =C65
B79: Column 3 | C79: 0 | D79: =C79+1 | E79: =D79+1 | F79: =E79+1 | G79: =F79+1 | H79: =G79+1 | I79: =H79+1 | J79: =I79+1 | K79: =J79+1 | ... BJ79: =BI79+1
B80: Monthly Gross Profit | D80: =SUM(Pricing!G56)
B84: Initial investment | C84: ='Pricing'!G52-'Pricing'!G7-'Pricing'!G100
B85: Cash flows | C85: =-C84 | D85: =IF(D$79<='Pricing'!G$4,'Pricing'!G$56,0) | E85: =IF(E$79<='Pricing'!G$4,'Pricing'!G$56,0) | F85: =IF(F$79<='Pricing'!G$4,'Pricing'!G$56,0) | G85: =IF(G$79<='Pricing'!G$4,'Pricing'!G$56,0) | H85: =IF(H$79<='Pricing'!G$4,'Pricing'!G$56,0) | I85: =IF(I$79<='Pricing'!G$4,'Pricing'!G$56,0) | J85: =IF(J$79<='Pricing'!G$4,'Pricing'!G$56,0) | K85: =IF(K$79<='Pricing'!G$4,'Pricing'!G$56,0) | L85: =IF(L$79<='Pricing'!G$4,'Pricing'!G$56,0) | M85: =IF(M$79<='Pricing'!G$4,'Pricing'!G$56,0) | N85: =IF(N$79<='Pricing'!G$4,'Pricing'!G$56,0) | O85: =IF(O$79<='Pricing'!G$4,'Pricing'!G$56,0) | P85: =IF(P$79<='Pricing'!G$4,'Pricing'!G$56,0) | Q85: =IF(Q$79<='Pricing'!G$4,'Pricing'!G$56,0) | R85: =IF(R$79<='Pricing'!G$4,'Pricing'!G$56,0) | S85: =IF(S$79<='Pricing'!G$4,'Pricing'!G$56,0) | T85: =IF(T$79<='Pricing'!G$4,'Pricing'!G$56,0) | U85: =IF(U$79<='Pricing'!G$4,'Pricing'!G$56,0) | V85: =IF(V$79<='Pricing'!G$4,'Pricing'!G$56,0) | W85: =IF(W$79<='Pricing'!G$4,'Pricing'!G$56,0) | X85: =IF(X$79<='Pricing'!G$4,'Pricing'!G$56,0) | Y85: =IF(Y$79<='Pricing'!G$4,'Pricing'!G$56,0) | Z85: =IF(Z$79<='Pricing'!G$4,'Pricing'!G$56,0) | AA85: =IF(AA$79<='Pricing'!G$4,'Pricing'!G$56,0) | AB85: =IF(AB$79<='Pricing'!G$4,'Pricing'!G$56,0) | AC85: =IF(AC$79<='Pricing'!G$4,'Pricing'!G$56,0) | AD85: =IF(AD$79<='Pricing'!G$4,'Pricing'!G$56,0) | AE85: =IF(AE$79<='Pricing'!G$4,'Pricing'!G$56,0) | AF85: =IF(AF$79<='Pricing'!G$4,'Pricing'!G$56,0) | AG85: =IF(AG$79<='Pricing'!G$4,'Pricing'!G$56,0) | AH85: =IF(AH$79<='Pricing'!G$4,'Pricing'!G$56,0) | AI85: =IF(AI$79<='Pricing'!G$4,'Pricing'!G$56,0) | AJ85: =IF(AJ$79<='Pricing'!G$4,'Pricing'!G$56,0) | AK85: =IF(AK$79<='Pricing'!G$4,'Pricing'!G$56,0) | AL85: =IF(AL$79<='Pricing'!G$4,'Pricing'!G$56,0) | AM85: =IF(AM$79<='Pricing'!G$4,'Pricing'!G$56,0) | AN85: =IF(AN$79<='Pricing'!G$4,'Pricing'!G$56,0) | AO85: =IF(AO$79<='Pricing'!G$4,'Pricing'!G$56,0) | AP85: =IF(AP$79<='Pricing'!G$4,'Pricing'!G$56,0) | AQ85: =IF(AQ$79<='Pricing'!G$4,'Pricing'!G$56,0) | AR85: =IF(AR$79<='Pricing'!G$4,'Pricing'!G$56,0) | AS85: =IF(AS$79<='Pricing'!G$4,'Pricing'!G$56,0) | AT85: =IF(AT$79<='Pricing'!G$4,'Pricing'!G$56,0) | AU85: =IF(AU$79<='Pricing'!G$4,'Pricing'!G$56,0) | AV85: =IF(AV$79<='Pricing'!G$4,'Pricing'!G$56,0) | AW85: =IF(AW$79<='Pricing'!G$4,'Pricing'!G$56,0) | AX85: =IF(AX$79<='Pricing'!G$4,'Pricing'!G$56,0) | AY85: =IF(AY$79<='Pricing'!G$4,'Pricing'!G$56,0) | AZ85: =IF(AZ$79<='Pricing'!G$4,'Pricing'!G$56,0) | BA85: =IF(BA$79<='Pricing'!G$4,'Pricing'!G$56,0) | BB85: =IF(BB$79<='Pricing'!G$4,'Pricing'!G$56,0) | BC85: =IF(BC$79<='Pricing'!G$4,'Pricing'!G$56,0) | BD85: =IF(BD$79<='Pricing'!G$4,'Pricing'!G$56,0) | BE85: =IF(BE$79<='Pricing'!G$4,'Pricing'!G$56,0) | BF85: =IF(BF$79<='Pricing'!G$4,'Pricing'!G$56,0) | BG85: =IF(BG$79<='Pricing'!G$4,'Pricing'!G$56,0) | BH85: =IF(BH$79<='Pricing'!G$4,'Pricing'!G$56,0) | BI85: =IF(BI$79<='Pricing'!G$4,'Pricing'!G$56,0) | BJ85: =IF(BJ$79<='Pricing'!G$4,'Pricing'!G$56,0)
B87: Cumulative cash flows | C87: =C85 | D87: =SUM($C85:D85) | E87: =SUM($C85:E85) | F87: =SUM($C85:F85) | G87: =SUM($C85:G85) | H87: =SUM($C85:H85) | I87: =SUM($C85:I85) | J87: =SUM($C85:J85) | K87: =SUM($C85:K85) | ... BJ87: =SUM($C85:BJ85)
D88: =IF(AND(C87<0,D87>=0,D85>0),-C87/D85,"n/m") | E88: =IF(AND(D87<0,E87>=0,E85>0),-D87/E85,"n/m") | F88: =IF(AND(E87<0,F87>=0,F85>0),-E87/F85,"n/m") | G88: =IF(AND(F87<0,G87>=0,G85>0),-F87/G85,"n/m") | H88: =IF(AND(G87<0,H87>=0,H85>0),-G87/H85,"n/m") | I88: =IF(AND(H87<0,I87>=0,I85>0),-H87/I85,"n/m") | J88: =IF(AND(I87<0,J87>=0,J85>0),-I87/J85,"n/m") | K88: =IF(AND(J87<0,K87>=0,K85>0),-J87/K85,"n/m") | ... BJ88: =IF(AND(BI87<0,BJ87>=0,BJ85>0),-BI87/BJ85,"n/m")
B91: Payback period | C91: =IF(C84<=0,0,IF(AND('Pricing'!G56>0,C84<='Pricing'!G56*'Pricing'!G4),C84/'Pricing'!G56,"n/m"))
B94: Breaking it down >
B95: The Integer | C95: =IF(ISNUMBER(C91),INT(C91),"n/m")
B96: The Fraction | C96: =IF(ISNUMBER(C91),MOD(C91,1),"n/m")
B99: Bonus: Payback period calculations in just one cell
B100: Payback period | C100: =C91
B105: Column 4 | C105: 0 | D105: =C105+1 | E105: =D105+1 | F105: =E105+1 | G105: =F105+1 | H105: =G105+1 | I105: =H105+1 | J105: =I105+1 | K105: =J105+1 | ... BJ105: =BI105+1
B106: Monthly Gross Profit | D106: =SUM(Pricing!H56)
B110: Initial investment | C110: ='Pricing'!H52-'Pricing'!H7-'Pricing'!H100
B111: Cash flows | C111: =-C110 | D111: =IF(D$105<='Pricing'!H$4,'Pricing'!H$56,0) | E111: =IF(E$105<='Pricing'!H$4,'Pricing'!H$56,0) | F111: =IF(F$105<='Pricing'!H$4,'Pricing'!H$56,0) | G111: =IF(G$105<='Pricing'!H$4,'Pricing'!H$56,0) | H111: =IF(H$105<='Pricing'!H$4,'Pricing'!H$56,0) | I111: =IF(I$105<='Pricing'!H$4,'Pricing'!H$56,0) | J111: =IF(J$105<='Pricing'!H$4,'Pricing'!H$56,0) | K111: =IF(K$105<='Pricing'!H$4,'Pricing'!H$56,0) | L111: =IF(L$105<='Pricing'!H$4,'Pricing'!H$56,0) | M111: =IF(M$105<='Pricing'!H$4,'Pricing'!H$56,0) | N111: =IF(N$105<='Pricing'!H$4,'Pricing'!H$56,0) | O111: =IF(O$105<='Pricing'!H$4,'Pricing'!H$56,0) | P111: =IF(P$105<='Pricing'!H$4,'Pricing'!H$56,0) | Q111: =IF(Q$105<='Pricing'!H$4,'Pricing'!H$56,0) | R111: =IF(R$105<='Pricing'!H$4,'Pricing'!H$56,0) | S111: =IF(S$105<='Pricing'!H$4,'Pricing'!H$56,0) | T111: =IF(T$105<='Pricing'!H$4,'Pricing'!H$56,0) | U111: =IF(U$105<='Pricing'!H$4,'Pricing'!H$56,0) | V111: =IF(V$105<='Pricing'!H$4,'Pricing'!H$56,0) | W111: =IF(W$105<='Pricing'!H$4,'Pricing'!H$56,0) | X111: =IF(X$105<='Pricing'!H$4,'Pricing'!H$56,0) | Y111: =IF(Y$105<='Pricing'!H$4,'Pricing'!H$56,0) | Z111: =IF(Z$105<='Pricing'!H$4,'Pricing'!H$56,0) | AA111: =IF(AA$105<='Pricing'!H$4,'Pricing'!H$56,0) | AB111: =IF(AB$105<='Pricing'!H$4,'Pricing'!H$56,0) | AC111: =IF(AC$105<='Pricing'!H$4,'Pricing'!H$56,0) | AD111: =IF(AD$105<='Pricing'!H$4,'Pricing'!H$56,0) | AE111: =IF(AE$105<='Pricing'!H$4,'Pricing'!H$56,0) | AF111: =IF(AF$105<='Pricing'!H$4,'Pricing'!H$56,0) | AG111: =IF(AG$105<='Pricing'!H$4,'Pricing'!H$56,0) | AH111: =IF(AH$105<='Pricing'!H$4,'Pricing'!H$56,0) | AI111: =IF(AI$105<='Pricing'!H$4,'Pricing'!H$56,0) | AJ111: =IF(AJ$105<='Pricing'!H$4,'Pricing'!H$56,0) | AK111: =IF(AK$105<='Pricing'!H$4,'Pricing'!H$56,0) | AL111: =IF(AL$105<='Pricing'!H$4,'Pricing'!H$56,0) | AM111: =IF(AM$105<='Pricing'!H$4,'Pricing'!H$56,0) | AN111: =IF(AN$105<='Pricing'!H$4,'Pricing'!H$56,0) | AO111: =IF(AO$105<='Pricing'!H$4,'Pricing'!H$56,0) | AP111: =IF(AP$105<='Pricing'!H$4,'Pricing'!H$56,0) | AQ111: =IF(AQ$105<='Pricing'!H$4,'Pricing'!H$56,0) | AR111: =IF(AR$105<='Pricing'!H$4,'Pricing'!H$56,0) | AS111: =IF(AS$105<='Pricing'!H$4,'Pricing'!H$56,0) | AT111: =IF(AT$105<='Pricing'!H$4,'Pricing'!H$56,0) | AU111: =IF(AU$105<='Pricing'!H$4,'Pricing'!H$56,0) | AV111: =IF(AV$105<='Pricing'!H$4,'Pricing'!H$56,0) | AW111: =IF(AW$105<='Pricing'!H$4,'Pricing'!H$56,0) | AX111: =IF(AX$105<='Pricing'!H$4,'Pricing'!H$56,0) | AY111: =IF(AY$105<='Pricing'!H$4,'Pricing'!H$56,0) | AZ111: =IF(AZ$105<='Pricing'!H$4,'Pricing'!H$56,0) | BA111: =IF(BA$105<='Pricing'!H$4,'Pricing'!H$56,0) | BB111: =IF(BB$105<='Pricing'!H$4,'Pricing'!H$56,0) | BC111: =IF(BC$105<='Pricing'!H$4,'Pricing'!H$56,0) | BD111: =IF(BD$105<='Pricing'!H$4,'Pricing'!H$56,0) | BE111: =IF(BE$105<='Pricing'!H$4,'Pricing'!H$56,0) | BF111: =IF(BF$105<='Pricing'!H$4,'Pricing'!H$56,0) | BG111: =IF(BG$105<='Pricing'!H$4,'Pricing'!H$56,0) | BH111: =IF(BH$105<='Pricing'!H$4,'Pricing'!H$56,0) | BI111: =IF(BI$105<='Pricing'!H$4,'Pricing'!H$56,0) | BJ111: =IF(BJ$105<='Pricing'!H$4,'Pricing'!H$56,0)
B113: Cumulative cash flows | C113: =C111 | D113: =SUM($C111:D111) | E113: =SUM($C111:E111) | F113: =SUM($C111:F111) | G113: =SUM($C111:G111) | H113: =SUM($C111:H111) | I113: =SUM($C111:I111) | J113: =SUM($C111:J111) | K113: =SUM($C111:K111) | ... BJ113: =SUM($C111:BJ111)
D114: =IF(AND(C113<0,D113>=0,D111>0),-C113/D111,"n/m") | E114: =IF(AND(D113<0,E113>=0,E111>0),-D113/E111,"n/m") | F114: =IF(AND(E113<0,F113>=0,F111>0),-E113/F111,"n/m") | G114: =IF(AND(F113<0,G113>=0,G111>0),-F113/G111,"n/m") | H114: =IF(AND(G113<0,H113>=0,H111>0),-G113/H111,"n/m") | I114: =IF(AND(H113<0,I113>=0,I111>0),-H113/I111,"n/m") | J114: =IF(AND(I113<0,J113>=0,J111>0),-I113/J111,"n/m") | K114: =IF(AND(J113<0,K113>=0,K111>0),-J113/K111,"n/m") | ... BJ114: =IF(AND(BI113<0,BJ113>=0,BJ111>0),-BI113/BJ111,"n/m")
B117: Payback period | C117: =IF(C110<=0,0,IF(AND('Pricing'!H56>0,C110<='Pricing'!H56*'Pricing'!H4),C110/'Pricing'!H56,"n/m"))
B120: Breaking it down >
B121: The Integer | C121: =IF(ISNUMBER(C117),INT(C117),"n/m")
B122: The Fraction | C122: =IF(ISNUMBER(C117),MOD(C117,1),"n/m")
B125: Bonus: Payback period calculations in just one cell
B126: Payback period | C126: =C117
B131: Column 5 | C131: 0 | D131: =C131+1 | E131: =D131+1 | F131: =E131+1 | G131: =F131+1 | H131: =G131+1 | I131: =H131+1 | J131: =I131+1 | K131: =J131+1 | ... BJ131: =BI131+1
B132: Monthly Gross Profit | D132: =SUM(Pricing!I56)
B136: Initial investment | C136: ='Pricing'!I52-'Pricing'!I7-'Pricing'!I100
B137: Cash flows | C137: =-C136 | D137: =IF(D$131<='Pricing'!I$4,'Pricing'!I$56,0) | E137: =IF(E$131<='Pricing'!I$4,'Pricing'!I$56,0) | F137: =IF(F$131<='Pricing'!I$4,'Pricing'!I$56,0) | G137: =IF(G$131<='Pricing'!I$4,'Pricing'!I$56,0) | H137: =IF(H$131<='Pricing'!I$4,'Pricing'!I$56,0) | I137: =IF(I$131<='Pricing'!I$4,'Pricing'!I$56,0) | J137: =IF(J$131<='Pricing'!I$4,'Pricing'!I$56,0) | K137: =IF(K$131<='Pricing'!I$4,'Pricing'!I$56,0) | L137: =IF(L$131<='Pricing'!I$4,'Pricing'!I$56,0) | M137: =IF(M$131<='Pricing'!I$4,'Pricing'!I$56,0) | N137: =IF(N$131<='Pricing'!I$4,'Pricing'!I$56,0) | O137: =IF(O$131<='Pricing'!I$4,'Pricing'!I$56,0) | P137: =IF(P$131<='Pricing'!I$4,'Pricing'!I$56,0) | Q137: =IF(Q$131<='Pricing'!I$4,'Pricing'!I$56,0) | R137: =IF(R$131<='Pricing'!I$4,'Pricing'!I$56,0) | S137: =IF(S$131<='Pricing'!I$4,'Pricing'!I$56,0) | T137: =IF(T$131<='Pricing'!I$4,'Pricing'!I$56,0) | U137: =IF(U$131<='Pricing'!I$4,'Pricing'!I$56,0) | V137: =IF(V$131<='Pricing'!I$4,'Pricing'!I$56,0) | W137: =IF(W$131<='Pricing'!I$4,'Pricing'!I$56,0) | X137: =IF(X$131<='Pricing'!I$4,'Pricing'!I$56,0) | Y137: =IF(Y$131<='Pricing'!I$4,'Pricing'!I$56,0) | Z137: =IF(Z$131<='Pricing'!I$4,'Pricing'!I$56,0) | AA137: =IF(AA$131<='Pricing'!I$4,'Pricing'!I$56,0) | AB137: =IF(AB$131<='Pricing'!I$4,'Pricing'!I$56,0) | AC137: =IF(AC$131<='Pricing'!I$4,'Pricing'!I$56,0) | AD137: =IF(AD$131<='Pricing'!I$4,'Pricing'!I$56,0) | AE137: =IF(AE$131<='Pricing'!I$4,'Pricing'!I$56,0) | AF137: =IF(AF$131<='Pricing'!I$4,'Pricing'!I$56,0) | AG137: =IF(AG$131<='Pricing'!I$4,'Pricing'!I$56,0) | AH137: =IF(AH$131<='Pricing'!I$4,'Pricing'!I$56,0) | AI137: =IF(AI$131<='Pricing'!I$4,'Pricing'!I$56,0) | AJ137: =IF(AJ$131<='Pricing'!I$4,'Pricing'!I$56,0) | AK137: =IF(AK$131<='Pricing'!I$4,'Pricing'!I$56,0) | AL137: =IF(AL$131<='Pricing'!I$4,'Pricing'!I$56,0) | AM137: =IF(AM$131<='Pricing'!I$4,'Pricing'!I$56,0) | AN137: =IF(AN$131<='Pricing'!I$4,'Pricing'!I$56,0) | AO137: =IF(AO$131<='Pricing'!I$4,'Pricing'!I$56,0) | AP137: =IF(AP$131<='Pricing'!I$4,'Pricing'!I$56,0) | AQ137: =IF(AQ$131<='Pricing'!I$4,'Pricing'!I$56,0) | AR137: =IF(AR$131<='Pricing'!I$4,'Pricing'!I$56,0) | AS137: =IF(AS$131<='Pricing'!I$4,'Pricing'!I$56,0) | AT137: =IF(AT$131<='Pricing'!I$4,'Pricing'!I$56,0) | AU137: =IF(AU$131<='Pricing'!I$4,'Pricing'!I$56,0) | AV137: =IF(AV$131<='Pricing'!I$4,'Pricing'!I$56,0) | AW137: =IF(AW$131<='Pricing'!I$4,'Pricing'!I$56,0) | AX137: =IF(AX$131<='Pricing'!I$4,'Pricing'!I$56,0) | AY137: =IF(AY$131<='Pricing'!I$4,'Pricing'!I$56,0) | AZ137: =IF(AZ$131<='Pricing'!I$4,'Pricing'!I$56,0) | BA137: =IF(BA$131<='Pricing'!I$4,'Pricing'!I$56,0) | BB137: =IF(BB$131<='Pricing'!I$4,'Pricing'!I$56,0) | BC137: =IF(BC$131<='Pricing'!I$4,'Pricing'!I$56,0) | BD137: =IF(BD$131<='Pricing'!I$4,'Pricing'!I$56,0) | BE137: =IF(BE$131<='Pricing'!I$4,'Pricing'!I$56,0) | BF137: =IF(BF$131<='Pricing'!I$4,'Pricing'!I$56,0) | BG137: =IF(BG$131<='Pricing'!I$4,'Pricing'!I$56,0) | BH137: =IF(BH$131<='Pricing'!I$4,'Pricing'!I$56,0) | BI137: =IF(BI$131<='Pricing'!I$4,'Pricing'!I$56,0) | BJ137: =IF(BJ$131<='Pricing'!I$4,'Pricing'!I$56,0)
B139: Cumulative cash flows | C139: =C137 | D139: =SUM($C137:D137) | E139: =SUM($C137:E137) | F139: =SUM($C137:F137) | G139: =SUM($C137:G137) | H139: =SUM($C137:H137) | I139: =SUM($C137:I137) | J139: =SUM($C137:J137) | K139: =SUM($C137:K137) | ... BJ139: =SUM($C137:BJ137)
D140: =IF(AND(C139<0,D139>=0,D137>0),-C139/D137,"n/m") | E140: =IF(AND(D139<0,E139>=0,E137>0),-D139/E137,"n/m") | F140: =IF(AND(E139<0,F139>=0,F137>0),-E139/F137,"n/m") | G140: =IF(AND(F139<0,G139>=0,G137>0),-F139/G137,"n/m") | H140: =IF(AND(G139<0,H139>=0,H137>0),-G139/H137,"n/m") | I140: =IF(AND(H139<0,I139>=0,I137>0),-H139/I137,"n/m") | J140: =IF(AND(I139<0,J139>=0,J137>0),-I139/J137,"n/m") | K140: =IF(AND(J139<0,K139>=0,K137>0),-J139/K137,"n/m") | ... BJ140: =IF(AND(BI139<0,BJ139>=0,BJ137>0),-BI139/BJ137,"n/m")
B143: Payback period | C143: =IF(C136<=0,0,IF(AND('Pricing'!I56>0,C136<='Pricing'!I56*'Pricing'!I4),C136/'Pricing'!I56,"n/m"))
B146: Breaking it down >
B147: The Integer | C147: =IF(ISNUMBER(C143),INT(C143),"n/m")
B148: The Fraction | C148: =IF(ISNUMBER(C143),MOD(C143,1),"n/m")
B151: Bonus: Payback period calculations in just one cell
B152: Payback period | C152: =C143

Sheet Exec Summary
B1: =Pricing!B1
B2: Business Case
B4: Date:
B5: Customer:
B6: Account Manager:
B7: Solution Engineer:
B8: Project Name:
B9: Project Description
B18: Financial Summary
B19: Rental | F19: Option 1 | H19: Option 2 | J19: Option 3 | L19: Option 4 | N19: Option 5
B20: Option Description | D20: → | F20: ='Pricing'!E3 | G20: 0 | H20: ='Pricing'!F3 | J20: ='Pricing'!G3 | L20: ='Pricing'!H3 | N20: ='Pricing'!I3
B21: Term (Months) | D21: → | F21: ='Pricing'!E4 | G21: =SUM(Pricing!F4) | H21: ='Pricing'!F4 | I21: =SUM(Pricing!H4) | J21: ='Pricing'!G4 | K21: =SUM(Pricing!J4) | L21: ='Pricing'!H4 | M21: =SUM(Pricing!L4) | N21: ='Pricing'!I4
B22: Number of Sites/Units | D22: → | F22: ='Pricing'!E5 | G22: =SUM(Pricing!F5) | H22: ='Pricing'!F5 | I22: =SUM(Pricing!H5) | J22: ='Pricing'!G5 | K22: =SUM(Pricing!J5) | L22: ='Pricing'!H5 | M22: =SUM(Pricing!L5) | N22: ='Pricing'!I5
B23: Costs | D23: Summary
B24: Capex | D24: ='Pricing'!D52 | F24: ='Pricing'!E52 | H24: ='Pricing'!F52 | J24: ='Pricing'!G52 | L24: ='Pricing'!H52 | N24: ='Pricing'!I52
B25: Labor | D25: ='Pricing'!D24 | F25: ='Pricing'!E24 | H25: ='Pricing'!F24 | J25: ='Pricing'!G24 | L25: ='Pricing'!H24 | N25: ='Pricing'!I24
B26: Operating Costs (Monthly) | D26: ='Pricing'!D53 | F26: ='Pricing'!E53 | H26: ='Pricing'!F53 | J26: ='Pricing'!G53 | L26: ='Pricing'!H53 | N26: ='Pricing'!I53
B27: Revenue
B28: Monthly Rate | D28: ='Pricing'!D55 | F28: ='Pricing'!E55 | H28: ='Pricing'!F55 | J28: ='Pricing'!G55 | L28: ='Pricing'!H55 | N28: ='Pricing'!I55
B29: Flat Rate Installation | D29: =SUM('Pricing'!E7:I7) | F29: ='Pricing'!E7 | H29: ='Pricing'!F7 | I29: =SUM(Pricing!G7) | J29: ='Pricing'!G7 | K29: =SUM(Pricing!I7) | L29: ='Pricing'!H7 | N29: ='Pricing'!I7
B30: TCV | D30: ='Pricing'!D54 | F30: ='Pricing'!E54 | H30: ='Pricing'!F54 | I30: =Pricing!G54 | J30: ='Pricing'!G54 | L30: ='Pricing'!H54 | N30: ='Pricing'!I54
B31: Monthly Gross Profit | D31: ='Pricing'!D56 | F31: ='Pricing'!E56 | H31: ='Pricing'!F56 | J31: ='Pricing'!G56 | L31: ='Pricing'!H56 | N31: ='Pricing'!I56
B32: Monthly Contribution Margin | D32: ='Pricing'!D57 | F32: ='Pricing'!E57 | H32: ='Pricing'!F57 | J32: ='Pricing'!G57 | L32: ='Pricing'!H57 | N32: ='Pricing'!I57
B33: NPV | D33: ='Pricing'!D58 | E33: =SUM(Pricing!D58) | F33: ='Pricing'!E58 | G33: =Pricing!F58 | H33: ='Pricing'!F58 | I33: =Pricing!H58 | J33: ='Pricing'!G58 | K33: =Pricing!J58 | L33: ='Pricing'!H58 | M33: =Pricing!L58 | N33: ='Pricing'!I58
B34: IRR | D34: ='Pricing'!D59 | E34: =SUM(Pricing!D59) | F34: ='Pricing'!E59 | G34: =Pricing!F59 | H34: ='Pricing'!F59 | I34: =Pricing!H59 | J34: ='Pricing'!G59 | K34: =Pricing!J59 | L34: ='Pricing'!H59 | M34: =Pricing!L59 | N34: ='Pricing'!I59
B35: Payback Period in Months | D35: ='Pricing'!D60 | F35: ='Pricing'!E60 | H35: ='Pricing'!F60 | J35: ='Pricing'!G60 | L35: ='Pricing'!H60 | N35: ='Pricing'!I60
B36: Cash Flow | D36: ='Pricing'!D61 | F36: ='Pricing'!E61 | H36: ='Pricing'!F61 | J36: ='Pricing'!G61 | L36: ='Pricing'!H61 | N36: ='Pricing'!I61
B38: Purchase | F38: Option 1 | H38: Option 2 | J38: Option 3 | L38: Option 4 | N38: Option 5
B39: Option Description | D39: → | F39: ='Pricing'!E64 | G39: ='Rental (BOM)'!E4 | H39: ='Pricing'!F64 | I39: ='Rental (BOM)'!G4 | J39: ='Pricing'!G64 | K39: ='Rental (BOM)'!I4 | L39: ='Pricing'!H64 | M39: ='Rental (BOM)'!K4 | N39: ='Pricing'!I64
B40: Number Packages (Same Configuration) | D40: → | F40: ='Pricing'!E65 | G40: =Pricing!F65 | H40: ='Pricing'!F65 | I40: =Pricing!H65 | J40: ='Pricing'!G65 | K40: =Pricing!J65 | L40: ='Pricing'!H65 | M40: =Pricing!L65 | N40: ='Pricing'!I65
D41: Summary
B42: Hardware Cost | D42: ='Pricing'!D97 | F42: ='Pricing'!E97 | H42: ='Pricing'!F97 | J42: ='Pricing'!G97 | L42: ='Pricing'!H97 | N42: ='Pricing'!I97
B43: Labor Cost | D43: ='Pricing'!D98 | F43: ='Pricing'!E98 | H43: ='Pricing'!F98 | J43: ='Pricing'!G98 | L43: ='Pricing'!H98 | N43: ='Pricing'!I98
B44: Sale Price | D44: ='Pricing'!D99 | F44: ='Pricing'!E99 | H44: ='Pricing'!F99 | J44: ='Pricing'!G99 | L44: ='Pricing'!H99 | N44: ='Pricing'!I99
B45: Deal Gross Profit | D45: ='Pricing'!D100 | F45: ='Pricing'!E100 | H45: ='Pricing'!F100 | J45: ='Pricing'!G100 | L45: ='Pricing'!H100 | N45: ='Pricing'!I100
B46: Contribution Margin | D46: ='Pricing'!D101 | F46: ='Pricing'!E101 | H46: ='Pricing'!F101 | J46: ='Pricing'!G101 | L46: ='Pricing'!H101 | N46: ='Pricing'!I101
B49: Approval Signatures
B51: CEO: | L51: Date:
B53: CFO: | L53: Date:
B55: Region GM and/or Area GM: | L55: Date:
B57: Sales Engineer and/or VP Engineering: | L57: Date:
B59: CCO and/or VP Sales | L59: Date:

Sheet NPV - IRR
A1: =Pricing!B1
B3: WACC | C3: 0.15 | D3: Cost of Capital
D5: COLUMN 1
C6: YEAR | D6: CAPEX | E6: Cash Flow | G6: Cumulative Cash Flow | I6: IRR | J6: =IFERROR(IRR(E7:E17),"n/m") | L6: Footnotes
B7: Year | C7: 0 | D7: ='Pricing'!E52-'Pricing'!E7-'Pricing'!E100 | E7: =-D7 | G7: =SUM(E$7:E7) | I7: NPV | J7: =NPV($C$3,E8:E17)+E7 | L7: Cash Flow is Calculated from Gross Margin Dollars
B8: Year | C8: 1 | E8: ='Pricing'!E$56*MAX(0,MIN(12,'Pricing'!E$4-(C8-1)*12)) | G8: =SUM(E$7:E8) | I8: Payback Month | J8: ='Pricing'!E60
B9: Year | C9: 2 | E9: ='Pricing'!E$56*MAX(0,MIN(12,'Pricing'!E$4-(C9-1)*12)) | G9: =SUM(E$7:E9) | K9: Notes/Comments/Assumptions
B10: Year | C10: 3 | E10: ='Pricing'!E$56*MAX(0,MIN(12,'Pricing'!E$4-(C10-1)*12)) | G10: =SUM(E$7:E10)
B11: Year | C11: 4 | E11: ='Pricing'!E$56*MAX(0,MIN(12,'Pricing'!E$4-(C11-1)*12)) | G11: =SUM(E$7:E11)
B12: Year | C12: 5 | E12: ='Pricing'!E$56*MAX(0,MIN(12,'Pricing'!E$4-(C12-1)*12)) | G12: =SUM(E$7:E12)
B13: Year | C13: 6 | E13: ='Pricing'!E$56*MAX(0,MIN(12,'Pricing'!E$4-(C13-1)*12)) | G13: =SUM(E$7:E13)
B14: Year | C14: 7 | E14: ='Pricing'!E$56*MAX(0,MIN(12,'Pricing'!E$4-(C14-1)*12)) | G14: =SUM(E$7:E14)
B15: Year | C15: 8 | E15: ='Pricing'!E$56*MAX(0,MIN(12,'Pricing'!E$4-(C15-1)*12)) | G15: =SUM(E$7:E15)
B16: Year | C16: 9 | E16: ='Pricing'!E$56*MAX(0,MIN(12,'Pricing'!E$4-(C16-1)*12)) | G16: =SUM(E$7:E16)
B17: Year | C17: 10 | E17: ='Pricing'!E$56*MAX(0,MIN(12,'Pricing'!E$4-(C17-1)*12)) | G17: =SUM(E$7:E17)
B18: Sum-PV | E18: =SUM(E7:E17)
D20: COLUMN 2
C21: YEAR | D21: CAPEX | E21: Cash Flow | G21: Cumulative Cash Flow | I21: IRR | J21: =IFERROR(IRR(E22:E32),"n/m")
B22: Year | C22: 0 | D22: ='Pricing'!F52-'Pricing'!F7-'Pricing'!F100 | E22: =-D22 | G22: =SUM(E$22:E22) | I22: NPV | J22: =NPV($C$3,E23:E32)+E22
B23: Year | C23: 1 | E23: ='Pricing'!F$56*MAX(0,MIN(12,'Pricing'!F$4-(C23-1)*12)) | G23: =SUM(E$22:E23) | I23: Payback Month | J23: ='Pricing'!F60 | K23: Notes/Comments/Assumptions
B24: Year | C24: 2 | E24: ='Pricing'!F$56*MAX(0,MIN(12,'Pricing'!F$4-(C24-1)*12)) | G24: =SUM(E$22:E24)
B25: Year | C25: 3 | E25: ='Pricing'!F$56*MAX(0,MIN(12,'Pricing'!F$4-(C25-1)*12)) | G25: =SUM(E$22:E25)
B26: Year | C26: 4 | E26: ='Pricing'!F$56*MAX(0,MIN(12,'Pricing'!F$4-(C26-1)*12)) | G26: =SUM(E$22:E26)
B27: Year | C27: 5 | E27: ='Pricing'!F$56*MAX(0,MIN(12,'Pricing'!F$4-(C27-1)*12)) | G27: =SUM(E$22:E27)
B28: Year | C28: 6 | E28: ='Pricing'!F$56*MAX(0,MIN(12,'Pricing'!F$4-(C28-1)*12)) | G28: =SUM(E$22:E28)
B29: Year | C29: 7 | E29: ='Pricing'!F$56*MAX(0,MIN(12,'Pricing'!F$4-(C29-1)*12)) | G29: =SUM(E$22:E29)
B30: Year | C30: 8 | E30: ='Pricing'!F$56*MAX(0,MIN(12,'Pricing'!F$4-(C30-1)*12)) | G30: =SUM(E$22:E30)
B31: Year | C31: 9 | E31: ='Pricing'!F$56*MAX(0,MIN(12,'Pricing'!F$4-(C31-1)*12)) | G31: =SUM(E$22:E31)
B32: Year | C32: 10 | E32: ='Pricing'!F$56*MAX(0,MIN(12,'Pricing'!F$4-(C32-1)*12)) | G32: =SUM(E$22:E32)
B33: Sum-PV | E33: =SUM(E22:E32)
D35: COLUMN 3
C36: YEAR | D36: CAPEX | E36: Cash Flow | I36: IRR | J36: =IFERROR(IRR(E37:E47),"n/m")
B37: Year | C37: 0 | D37: ='Pricing'!G52-'Pricing'!G7-'Pricing'!G100 | E37: =-D37 | G37: =E37/((1+$C$3)^C37)
B38: Year | C38: 1 | E38: ='Pricing'!G$56*MAX(0,MIN(12,'Pricing'!G$4-(C38-1)*12)) | G38: =E38/((1+$C$3)^C38) | K38: Notes/Comments/Assumptions
B39: Year | C39: 2 | E39: ='Pricing'!G$56*MAX(0,MIN(12,'Pricing'!G$4-(C39-1)*12)) | G39: =E39/((1+$C$3)^C39)
B40: Year | C40: 3 | E40: ='Pricing'!G$56*MAX(0,MIN(12,'Pricing'!G$4-(C40-1)*12)) | G40: =E40/((1+$C$3)^C40)
B41: Year | C41: 4 | E41: ='Pricing'!G$56*MAX(0,MIN(12,'Pricing'!G$4-(C41-1)*12)) | G41: =E41/((1+$C$3)^C41)
B42: Year | C42: 5 | E42: ='Pricing'!G$56*MAX(0,MIN(12,'Pricing'!G$4-(C42-1)*12)) | G42: =E42/((1+$C$3)^C42)
B43: Year | C43: 6 | E43: ='Pricing'!G$56*MAX(0,MIN(12,'Pricing'!G$4-(C43-1)*12)) | G43: =E43/((1+$C$3)^C43)
B44: Year | C44: 7 | E44: ='Pricing'!G$56*MAX(0,MIN(12,'Pricing'!G$4-(C44-1)*12)) | G44: =E44/((1+$C$3)^C44)
B45: Year | C45: 8 | E45: ='Pricing'!G$56*MAX(0,MIN(12,'Pricing'!G$4-(C45-1)*12)) | G45: =E45/((1+$C$3)^C45)
B46: Year | C46: 9 | E46: ='Pricing'!G$56*MAX(0,MIN(12,'Pricing'!G$4-(C46-1)*12)) | G46: =E46/((1+$C$3)^C46)
B47: Year | C47: 10 | E47: ='Pricing'!G$56*MAX(0,MIN(12,'Pricing'!G$4-(C47-1)*12)) | G47: =E47/((1+$C$3)^C47)
B48: Sum-PV | E48: =SUM(E37:E47) | G48: =SUM(G37:G47)
D50: COLUMN 4
C51: YEAR | D51: CAPEX | E51: Cash Flow | I51: IRR | J51: =IFERROR(IRR(E52:E62),"n/m")
B52: Year | C52: 0 | D52: ='Pricing'!H52-'Pricing'!H7-'Pricing'!H100 | E52: =-D52 | G52: =E52/((1+$C$3)^C52)
B53: Year | C53: 1 | E53: ='Pricing'!H$56*MAX(0,MIN(12,'Pricing'!H$4-(C53-1)*12)) | G53: =E53/((1+$C$3)^C53) | K53: Notes/Comments/Assumptions
B54: Year | C54: 2 | E54: ='Pricing'!H$56*MAX(0,MIN(12,'Pricing'!H$4-(C54-1)*12)) | G54: =E54/((1+$C$3)^C54)
B55: Year | C55: 3 | E55: ='Pricing'!H$56*MAX(0,MIN(12,'Pricing'!H$4-(C55-1)*12)) | G55: =E55/((1+$C$3)^C55)
B56: Year | C56: 4 | E56: ='Pricing'!H$56*MAX(0,MIN(12,'Pricing'!H$4-(C56-1)*12)) | G56: =E56/((1+$C$3)^C56)
B57: Year | C57: 5 | E57: ='Pricing'!H$56*MAX(0,MIN(12,'Pricing'!H$4-(C57-1)*12)) | G57: =E57/((1+$C$3)^C57)
B58: Year | C58: 6 | E58: ='Pricing'!H$56*MAX(0,MIN(12,'Pricing'!H$4-(C58-1)*12)) | G58: =E58/((1+$C$3)^C58)
B59: Year | C59: 7 | E59: ='Pricing'!H$56*MAX(0,MIN(12,'Pricing'!H$4-(C59-1)*12)) | G59: =E59/((1+$C$3)^C59)
B60: Year | C60: 8 | E60: ='Pricing'!H$56*MAX(0,MIN(12,'Pricing'!H$4-(C60-1)*12)) | G60: =E60/((1+$C$3)^C60)
B61: Year | C61: 9 | E61: ='Pricing'!H$56*MAX(0,MIN(12,'Pricing'!H$4-(C61-1)*12)) | G61: =E61/((1+$C$3)^C61)
B62: Year | C62: 10 | E62: ='Pricing'!H$56*MAX(0,MIN(12,'Pricing'!H$4-(C62-1)*12)) | G62: =E62/((1+$C$3)^C62)
B63: Sum-PV | E63: =SUM(E52:E62) | G63: =SUM(G52:G62)
D65: COLUMN 5
C66: YEAR | D66: CAPEX | E66: Cash Flow | I66: IRR | J66: =IFERROR(IRR(E67:E77),"n/m")
B67: Year | C67: 0 | D67: ='Pricing'!I52-'Pricing'!I7-'Pricing'!I100 | E67: =-D67 | G67: =E67/((1+$C$3)^C67)
B68: Year | C68: 1 | E68: ='Pricing'!I$56*MAX(0,MIN(12,'Pricing'!I$4-(C68-1)*12)) | G68: =E68/((1+$C$3)^C68) | K68: Notes/Comments/Assumptions
B69: Year | C69: 2 | E69: ='Pricing'!I$56*MAX(0,MIN(12,'Pricing'!I$4-(C69-1)*12)) | G69: =E69/((1+$C$3)^C69)
B70: Year | C70: 3 | E70: ='Pricing'!I$56*MAX(0,MIN(12,'Pricing'!I$4-(C70-1)*12)) | G70: =E70/((1+$C$3)^C70)
B71: Year | C71: 4 | E71: ='Pricing'!I$56*MAX(0,MIN(12,'Pricing'!I$4-(C71-1)*12)) | G71: =E71/((1+$C$3)^C71)
B72: Year | C72: 5 | E72: ='Pricing'!I$56*MAX(0,MIN(12,'Pricing'!I$4-(C72-1)*12)) | G72: =E72/((1+$C$3)^C72)
B73: Year | C73: 6 | E73: ='Pricing'!I$56*MAX(0,MIN(12,'Pricing'!I$4-(C73-1)*12)) | G73: =E73/((1+$C$3)^C73)
B74: Year | C74: 7 | E74: ='Pricing'!I$56*MAX(0,MIN(12,'Pricing'!I$4-(C74-1)*12)) | G74: =E74/((1+$C$3)^C74)
B75: Year | C75: 8 | E75: ='Pricing'!I$56*MAX(0,MIN(12,'Pricing'!I$4-(C75-1)*12)) | G75: =E75/((1+$C$3)^C75)
B76: Year | C76: 9 | E76: ='Pricing'!I$56*MAX(0,MIN(12,'Pricing'!I$4-(C76-1)*12)) | G76: =E76/((1+$C$3)^C76)
B77: Year | C77: 10 | E77: ='Pricing'!I$56*MAX(0,MIN(12,'Pricing'!I$4-(C77-1)*12)) | G77: =E77/((1+$C$3)^C77)
B78: Sum-PV | E78: =SUM(E67:E77) | G78: =SUM(G67:G77)
